{"directed": true, "multigraph": false, "graph": {}, "nodes": [{"object": "x0", "name": ["__background__", "pans", "pikachu"], "weight": [1.0, 1.0, 1.0], "id": 0}, {"object": "x1", "name": ["__background__", "pans", "pikachu"], "weight": [1.0, 1.0, 1.0], "id": 1}, {"object": "x2", "name": ["__background__", "pans", "pikachu"], "weight": [1.0, 1.0, 1.0], "id": 2}, {"object": "x3", "name": ["__background__", "pans", "pikachu"], "weight": [1.0, 1.0, 1.0], "id": 3}, {"object": "x4", "name": ["__background__", "pans", "pikachu"], "weight": [1.0, 1.0, 1.0], "id": 4}, {"object": "x5", "name": ["__background__", "pans", "pikachu"], "weight": [1.0, 1.0, 1.0], "id": 5}, {"object": "x6", "name": ["__background__", "pans", "pikachu"], "weight": [1.0, 1.0, 1.0], "id": 6}, {"object": "x7", "name": ["__background__", "pans", "pikachu"], "weight": [1.0, 1.0, 1.0], "id": 7}, {"object": "x8", "name": ["__background__", "pans", "pikachu"], "weight": [1.0, 1.0, 1.0], "id": 8}, {"object": "x9", "name": ["__background__", "pans", "pikachu"], "weight": [1.0, 1.0, 1.0], "id": 9}, {"object": "x10", "name": ["__background__", "pans", "pikachu"], "weight": [1.0, 1.0, 1.0], "id": 10}, {"object": "x11", "name": ["__background__", "pans", "pikachu"], "weight": [1.0, 1.0, 1.0], "id": 11}, {"object": "x12", "name": ["__background__", "pans", "pikachu"], "weight": [1.0, 1.0, 1.0], "id": 12}, {"object": "x13", "name": ["__background__", "pans", "pikachu"], "weight": [1.0, 1.0, 1.0], "id": 13}, {"object": "x14", "name": ["__background__", "pans", "pikachu"], "weight": [1.0, 1.0, 1.0], "id": 14}, {"object": "x15", "name": ["__background__", "pans", "pikachu"], "weight": [1.0, 1.0, 1.0], "id": 15}, {"object": "x16", "name": ["__background__", "pans", "pikachu"], "weight": [1.0, 1.0, 1.0], "id": 16}, {"object": "x17", "name": ["__background__", "pans", "pikachu"], "weight": [1.0, 1.0, 1.0], "id": 17}, {"name": ["rectangular"], "weight": [0.9984833998025064], "id": 18}, {"name": ["angry", "lined"], "weight": [0.9885378371476411, 0.9880087313492193], "id": 19}, {"name": ["pointing"], "weight": [0.994035325224527], "id": 20}, {"name": ["bottom"], "weight": [1.0], "id": 21}, {"name": ["left"], "weight": [1.0], "id": 22}, {"name": ["bottom"], "weight": [1.0], "id": 23}, {"name": ["right"], "weight": [1.0], "id": 24}, {"name": ["top"], "weight": [1.0], "id": 25}, {"name": ["right"], "weight": [1.0], "id": 26}, {"name": ["top"], "weight": [1.0], "id": 27}, {"name": ["left"], "weight": [1.0], "id": 28}, {"name": ["bottom"], "weight": [1.0], "id": 29}, {"name": ["left"], "weight": [1.0], "id": 30}, {"name": ["bottom"], "weight": [1.0], "id": 31}, {"name": ["right"], "weight": [1.0], "id": 32}, {"name": ["top"], "weight": [1.0], "id": 33}, {"name": ["right"], "weight": [1.0], "id": 34}, {"name": ["top"], "weight": [1.0], "id": 35}, {"name": ["right"], "weight": [1.0], "id": 36}, {"name": ["top"], "weight": [1.0], "id": 37}, {"name": ["right"], "weight": [1.0], "id": 38}, {"name": ["top"], "weight": [1.0], "id": 39}, {"name": ["right"], "weight": [1.0], "id": 40}, {"name": ["bottom"], "weight": [1.0], "id": 41}, {"name": ["left"], "weight": [1.0], "id": 42}, {"name": ["top"], "weight": [1.0], "id": 43}, {"name": ["left"], "weight": [1.0], "id": 44}, {"name": ["top"], "weight": [1.0], "id": 45}, {"name": ["left"], "weight": [1.0], "id": 46}, {"name": ["bottom"], "weight": [1.0], "id": 47}, {"name": ["left"], "weight": [1.0], "id": 48}, {"name": ["bottom"], "weight": [1.0], "id": 49}, {"name": ["left"], "weight": [1.0], "id": 50}, {"name": ["top"], "weight": [1.0], "id": 51}, {"name": ["left"], "weight": [1.0], "id": 52}, {"name": ["top"], "weight": [1.0], "id": 53}, {"name": ["left"], "weight": [1.0], "id": 54}, {"name": ["top"], "weight": [1.0], "id": 55}, {"name": ["right"], "weight": [1.0], "id": 56}], "links": [{"id": 18, "name": ["has shape"], "weight": [1.0], "source": 0, "target": 18}, {"id": 19, "name": ["has property"], "weight": [1.0], "source": 0, "target": 19}, {"id": 20, "name": ["has pose"], "weight": [1.0], "source": 0, "target": 20}, {"id": 21, "name": ["has vposition"], "weight": [1.0], "source": 0, "target": 21}, {"id": 22, "name": ["has hposition"], "weight": [1.0], "source": 0, "target": 22}, {"id": 23, "name": ["has vposition"], "weight": [1.0], "source": 1, "target": 23}, {"id": 24, "name": ["has hposition"], "weight": [1.0], "source": 1, "target": 24}, {"id": 14, "name": ["drawn on", "reflecting in", "lying inside"], "weight": [0.33339812495228144, 0.33334866603496843, 0.33325320901275013], "source": 2, "target": 14}, {"id": 10, "name": ["hanging above", "working in", "mounted to"], "weight": [0.3339380406637353, 0.33354399353434255, 0.33251796580192217], "source": 2, "target": 10}, {"id": 2, "name": ["floating in", "crossing", "sitting on top of"], "weight": [0.3351881845984883, 0.3335417984355637, 0.33127001696594804], "source": 2, "target": 2}, {"id": 4, "name": ["touching", "skiing on", "coming from"], "weight": [0.33565412971742586, 0.33305628308472385, 0.3312895871978503], "source": 2, "target": 4}, {"id": 13, "name": ["hanging from", "mixed with", "on the edge of"], "weight": [0.3343412896962356, 0.3341620830993103, 0.33149662720445416], "source": 2, "target": 13}, {"id": 15, "name": ["reflected on", "running in", "worn on"], "weight": [0.33375944867262936, 0.3332508220939416, 0.3329897292334291], "source": 2, "target": 15}, {"id": 12, "name": ["carrying", "underneath", "walking down"], "weight": [0.3338737665682158, 0.33366536348420217, 0.332460869947582], "source": 2, "target": 12}, {"id": 11, "name": ["picking up", "sitting at", "blowing out"], "weight": [0.3337316108476545, 0.33327487341973044, 0.332993515732615], "source": 2, "target": 11}, {"id": 7, "name": ["flying in", "jumping on", "using"], "weight": [0.33369549663151477, 0.33347149035473267, 0.3328330130137526], "source": 2, "target": 7}, {"id": 6, "name": ["running on", "eating at", "standing under"], "weight": [0.3340075875844255, 0.3332850403099458, 0.33270737210562873], "source": 2, "target": 6}, {"id": 8, "name": ["sitting inside", "flying in", "helping"], "weight": [0.33413456299345917, 0.3334577732829409, 0.3324076637236], "source": 2, "target": 8}, {"id": 9, "name": ["sitting on", "drinking", "contain"], "weight": [0.33416485900587384, 0.33344348218762915, 0.332391658806497], "source": 2, "target": 9}, {"id": 25, "name": ["has vposition"], "weight": [1.0], "source": 2, "target": 25}, {"id": 26, "name": ["has hposition"], "weight": [1.0], "source": 2, "target": 26}, {"id": 27, "name": ["has vposition"], "weight": [1.0], "source": 3, "target": 27}, {"id": 28, "name": ["has hposition"], "weight": [1.0], "source": 3, "target": 28}, {"id": 7, "name": ["lying on", "lying in", "walking along"], "weight": [0.3339601445492218, 0.33374318717275364, 0.3322966682780245], "source": 4, "target": 7}, {"id": 8, "name": ["drawn on", "walking to", "going through"], "weight": [0.3342912598916961, 0.3329516677625295, 0.33275707234577445], "source": 4, "target": 8}, {"id": 15, "name": ["walking up", "to the left of", "sitting inside"], "weight": [0.3336864658258919, 0.3332051025641945, 0.3331084316099136], "source": 4, "target": 15}, {"id": 2, "name": ["climbing", "tied around", "driving on"], "weight": [0.3345803313020953, 0.33342777476533136, 0.3319918939325734], "source": 4, "target": 2}, {"id": 6, "name": ["observing", "skiing on", "longer than"], "weight": [0.3340369650559265, 0.333078409485678, 0.3328846254583956], "source": 4, "target": 6}, {"id": 9, "name": ["hanging above", "on the front of", "serving"], "weight": [0.3337276205752067, 0.33327334669155534, 0.33299903273323783], "source": 4, "target": 9}, {"id": 12, "name": ["mounted to", "hitting", "reading"], "weight": [0.33367579857266033, 0.3333267019290597, 0.33299749949827995], "source": 4, "target": 12}, {"id": 29, "name": ["has vposition"], "weight": [1.0], "source": 4, "target": 29}, {"id": 30, "name": ["has hposition"], "weight": [1.0], "source": 4, "target": 30}, {"id": 31, "name": ["has vposition"], "weight": [1.0], "source": 5, "target": 31}, {"id": 32, "name": ["has hposition"], "weight": [1.0], "source": 5, "target": 32}, {"id": 2, "name": ["trying to catch", "pulling", "driving"], "weight": [0.33350210853205203, 0.3333162464176317, 0.33318164505031633], "source": 6, "target": 2}, {"id": 10, "name": ["sitting in", "licking", "playing in"], "weight": [0.3355524569703859, 0.33353542759054744, 0.3309121154390667], "source": 6, "target": 10}, {"id": 4, "name": ["jumping off", "hung on", "pushed by"], "weight": [0.33378429284855154, 0.333425399378237, 0.33279030777321134], "source": 6, "target": 4}, {"id": 33, "name": ["has vposition"], "weight": [1.0], "source": 6, "target": 33}, {"id": 34, "name": ["has hposition"], "weight": [1.0], "source": 6, "target": 34}, {"id": 4, "name": ["hung on", "filled with", "flying above"], "weight": [0.33418212014760085, 0.3329996393700006, 0.33281824048239855], "source": 7, "target": 4}, {"id": 2, "name": ["coming from", "wrapped in", "lying inside"], "weight": [0.33446461566240737, 0.3340743132968001, 0.3314610710407926], "source": 7, "target": 2}, {"id": 10, "name": ["walking toward", "tied to", "growing next to"], "weight": [0.33368779132662646, 0.3334818003619309, 0.3328304083114426], "source": 7, "target": 10}, {"id": 35, "name": ["has vposition"], "weight": [1.0], "source": 7, "target": 35}, {"id": 36, "name": ["has hposition"], "weight": [1.0], "source": 7, "target": 36}, {"id": 4, "name": ["exiting", "biting", "looking at"], "weight": [0.33627973435113073, 0.3320659601822253, 0.331654305466644], "source": 8, "target": 4}, {"id": 10, "name": ["approaching", "grabbing", "underneath"], "weight": [0.3341939097492872, 0.3332074051138741, 0.3325986851368387], "source": 8, "target": 10}, {"id": 2, "name": ["jumping over", "mounted to", "walking into"], "weight": [0.3343580774505703, 0.3330660365580067, 0.332575885991423], "source": 8, "target": 2}, {"id": 37, "name": ["has vposition"], "weight": [1.0], "source": 8, "target": 37}, {"id": 38, "name": ["has hposition"], "weight": [1.0], "source": 8, "target": 38}, {"id": 2, "name": ["getting on", "eating from", "skating on"], "weight": [0.333607851687823, 0.3333937102711965, 0.3329984380409805], "source": 9, "target": 2}, {"id": 4, "name": ["eating at", "standing in", "sniffing"], "weight": [0.33464094739618255, 0.3333167466485111, 0.3320423059553063], "source": 9, "target": 4}, {"id": 10, "name": ["parked alongside", "preparing", "lying next to"], "weight": [0.33345705658852304, 0.3334480530685623, 0.33309489034291456], "source": 9, "target": 10}, {"id": 39, "name": ["has vposition"], "weight": [1.0], "source": 9, "target": 39}, {"id": 40, "name": ["has hposition"], "weight": [1.0], "source": 9, "target": 40}, {"id": 9, "name": ["grazing on", "sitting under", "seen through"], "weight": [0.33438301530244063, 0.3336859185492764, 0.33193106614828294], "source": 10, "target": 9}, {"id": 12, "name": ["running in", "parked by", "next to"], "weight": [0.3354265484606439, 0.3329562985962134, 0.33161715294314276], "source": 10, "target": 12}, {"id": 2, "name": ["cooked in", "riding in", "boarding"], "weight": [0.3335781347928882, 0.33349967095176086, 0.33292219425535086], "source": 10, "target": 2}, {"id": 8, "name": ["biting", "floating in", "drawn on"], "weight": [0.33368613509852246, 0.3332726882528334, 0.3330411766486441], "source": 10, "target": 8}, {"id": 6, "name": ["coming down", "standing next to", "walking into"], "weight": [0.3349650268523043, 0.3327170099462553, 0.33231796320144036], "source": 10, "target": 6}, {"id": 7, "name": ["parked near", "resting on", "reflected in"], "weight": [0.33467382734270024, 0.3340159494181184, 0.33131022323918136], "source": 10, "target": 7}, {"id": 15, "name": ["kept in", "sitting at", "traveling on"], "weight": [0.3347577171440493, 0.33277095197609513, 0.3324713308798556], "source": 10, "target": 15}, {"id": 41, "name": ["has vposition"], "weight": [1.0], "source": 10, "target": 41}, {"id": 42, "name": ["has hposition"], "weight": [1.0], "source": 10, "target": 42}, {"id": 12, "name": ["sewn on", "flying over", "walking on"], "weight": [0.33356645687262454, 0.3335295560649457, 0.3329039870624298], "source": 11, "target": 12}, {"id": 11, "name": ["sitting at", "sitting in front of", "looking at"], "weight": [0.335031548761582, 0.3326665143326433, 0.33230193690577475], "source": 11, "target": 11}, {"id": 2, "name": ["going through", "served on", "lying inside"], "weight": [0.3338348392921284, 0.33351952638020893, 0.3326456343276627], "source": 11, "target": 2}, {"id": 43, "name": ["has vposition"], "weight": [1.0], "source": 11, "target": 43}, {"id": 44, "name": ["has hposition"], "weight": [1.0], "source": 11, "target": 44}, {"id": 2, "name": ["lying on", "walking with", "on the back of"], "weight": [0.33371119208265515, 0.3333873046821062, 0.33290150323523865], "source": 12, "target": 2}, {"id": 10, "name": ["wrapped around", "jumping off", "hanging out of"], "weight": [0.33447916019601726, 0.3335533806462642, 0.3319674591577185], "source": 12, "target": 10}, {"id": 4, "name": ["driving down", "walking down", "parked behind"], "weight": [0.3340288455402616, 0.33386030983879184, 0.33211084462094653], "source": 12, "target": 4}, {"id": 45, "name": ["has vposition"], "weight": [1.0], "source": 12, "target": 45}, {"id": 46, "name": ["has hposition"], "weight": [1.0], "source": 12, "target": 46}, {"name": ["reverse sewn on", "reverse flying over", "reverse walking on"], "id": 11, "weight": [0.33356645687262454, 0.3335295560649457, 0.3329039870624298], "source": 12, "target": 11}, {"name": ["reverse between", "reverse grazing in", "reverse parked near"], "id": 15, "weight": [0.33372360616661106, 0.33331451266929385, 0.33296188116409503], "source": 12, "target": 15}, {"id": 2, "name": ["grazing in", "cooking", "parked in"], "weight": [0.33435728993076747, 0.3330033000064252, 0.33263941006280734], "source": 13, "target": 2}, {"id": 47, "name": ["has vposition"], "weight": [1.0], "source": 13, "target": 47}, {"id": 48, "name": ["has hposition"], "weight": [1.0], "source": 13, "target": 48}, {"name": ["reverse sitting in front of", "reverse pushing", "reverse flying"], "id": 14, "weight": [0.3341695979071641, 0.3339508879311086, 0.3318795141617273], "source": 13, "target": 14}, {"id": 2, "name": ["hang from", "draped over", "eating at"], "weight": [0.33459552810707827, 0.3343120532835479, 0.3310924186093738], "source": 14, "target": 2}, {"id": 13, "name": ["sitting in front of", "pushing", "flying"], "weight": [0.3341695979071641, 0.3339508879311086, 0.3318795141617273], "source": 14, "target": 13}, {"id": 49, "name": ["has vposition"], "weight": [1.0], "source": 14, "target": 49}, {"id": 50, "name": ["has hposition"], "weight": [1.0], "source": 14, "target": 50}, {"id": 2, "name": ["growing along", "walking in", "sprinkled on"], "weight": [0.33574068172134935, 0.33221736553981246, 0.33204195273883813], "source": 15, "target": 2}, {"id": 15, "name": ["in", "coming down", "hanging from"], "weight": [0.3343491224872177, 0.3334142955871926, 0.33223658192558975], "source": 15, "target": 15}, {"id": 12, "name": ["between", "grazing in", "parked near"], "weight": [0.33372360616661106, 0.33331451266929385, 0.33296188116409503], "source": 15, "target": 12}, {"id": 10, "name": ["worn on", "sitting in", "leading"], "weight": [0.3336930630750463, 0.33327224660811255, 0.33303469031684113], "source": 15, "target": 10}, {"id": 4, "name": ["flying in", "mounted on", "wearing"], "weight": [0.3350991181186459, 0.3348097689143382, 0.33009111296701593], "source": 15, "target": 4}, {"id": 51, "name": ["has vposition"], "weight": [1.0], "source": 15, "target": 51}, {"id": 52, "name": ["has hposition"], "weight": [1.0], "source": 15, "target": 52}, {"id": 53, "name": ["has vposition"], "weight": [1.0], "source": 16, "target": 53}, {"id": 54, "name": ["has hposition"], "weight": [1.0], "source": 16, "target": 54}, {"id": 55, "name": ["has vposition"], "weight": [1.0], "source": 17, "target": 55}, {"id": 56, "name": ["has hposition"], "weight": [1.0], "source": 17, "target": 56}, {"name": ["reverse has shape"], "id": 0, "weight": [1.0], "source": 18, "target": 0}, {"name": ["reverse has property"], "id": 0, "weight": [1.0], "source": 19, "target": 0}, {"name": ["reverse has pose"], "id": 0, "weight": [1.0], "source": 20, "target": 0}, {"name": ["reverse has vposition"], "id": 0, "weight": [1.0], "source": 21, "target": 0}, {"name": ["reverse has hposition"], "id": 0, "weight": [1.0], "source": 22, "target": 0}, {"name": ["reverse has vposition"], "id": 1, "weight": [1.0], "source": 23, "target": 1}, {"name": ["reverse has hposition"], "id": 1, "weight": [1.0], "source": 24, "target": 1}, {"name": ["reverse has vposition"], "id": 2, "weight": [1.0], "source": 25, "target": 2}, {"name": ["reverse has hposition"], "id": 2, "weight": [1.0], "source": 26, "target": 2}, {"name": ["reverse has vposition"], "id": 3, "weight": [1.0], "source": 27, "target": 3}, {"name": ["reverse has hposition"], "id": 3, "weight": [1.0], "source": 28, "target": 3}, {"name": ["reverse has vposition"], "id": 4, "weight": [1.0], "source": 29, "target": 4}, {"name": ["reverse has hposition"], "id": 4, "weight": [1.0], "source": 30, "target": 4}, {"name": ["reverse has vposition"], "id": 5, "weight": [1.0], "source": 31, "target": 5}, {"name": ["reverse has hposition"], "id": 5, "weight": [1.0], "source": 32, "target": 5}, {"name": ["reverse has vposition"], "id": 6, "weight": [1.0], "source": 33, "target": 6}, {"name": ["reverse has hposition"], "id": 6, "weight": [1.0], "source": 34, "target": 6}, {"name": ["reverse has vposition"], "id": 7, "weight": [1.0], "source": 35, "target": 7}, {"name": ["reverse has hposition"], "id": 7, "weight": [1.0], "source": 36, "target": 7}, {"name": ["reverse has vposition"], "id": 8, "weight": [1.0], "source": 37, "target": 8}, {"name": ["reverse has hposition"], "id": 8, "weight": [1.0], "source": 38, "target": 8}, {"name": ["reverse has vposition"], "id": 9, "weight": [1.0], "source": 39, "target": 9}, {"name": ["reverse has hposition"], "id": 9, "weight": [1.0], "source": 40, "target": 9}, {"name": ["reverse has vposition"], "id": 10, "weight": [1.0], "source": 41, "target": 10}, {"name": ["reverse has hposition"], "id": 10, "weight": [1.0], "source": 42, "target": 10}, {"name": ["reverse has vposition"], "id": 11, "weight": [1.0], "source": 43, "target": 11}, {"name": ["reverse has hposition"], "id": 11, "weight": [1.0], "source": 44, "target": 11}, {"name": ["reverse has vposition"], "id": 12, "weight": [1.0], "source": 45, "target": 12}, {"name": ["reverse has hposition"], "id": 12, "weight": [1.0], "source": 46, "target": 12}, {"name": ["reverse has vposition"], "id": 13, "weight": [1.0], "source": 47, "target": 13}, {"name": ["reverse has hposition"], "id": 13, "weight": [1.0], "source": 48, "target": 13}, {"name": ["reverse has vposition"], "id": 14, "weight": [1.0], "source": 49, "target": 14}, {"name": ["reverse has hposition"], "id": 14, "weight": [1.0], "source": 50, "target": 14}, {"name": ["reverse has vposition"], "id": 15, "weight": [1.0], "source": 51, "target": 15}, {"name": ["reverse has hposition"], "id": 15, "weight": [1.0], "source": 52, "target": 15}, {"name": ["reverse has vposition"], "id": 16, "weight": [1.0], "source": 53, "target": 16}, {"name": ["reverse has hposition"], "id": 16, "weight": [1.0], "source": 54, "target": 16}, {"name": ["reverse has vposition"], "id": 17, "weight": [1.0], "source": 55, "target": 17}, {"name": ["reverse has hposition"], "id": 17, "weight": [1.0], "source": 56, "target": 17}]}