{"directed": true, "multigraph": false, "graph": {}, "nodes": [{"object": "x0", "name": ["__background__", "pans", "pikachu"], "weight": [1.0, 1.0, 1.0], "id": 0}, {"object": "x1", "name": ["__background__", "pans", "pikachu"], "weight": [1.0, 1.0, 1.0], "id": 1}, {"object": "x2", "name": ["__background__", "pans", "pikachu"], "weight": [1.0, 1.0, 1.0], "id": 2}, {"object": "x3", "name": ["__background__", "pans", "pikachu"], "weight": [1.0, 1.0, 1.0], "id": 3}, {"object": "x4", "name": ["__background__", "pans", "pikachu"], "weight": [1.0, 1.0, 1.0], "id": 4}, {"object": "x5", "name": ["__background__", "pans", "pikachu"], "weight": [1.0, 1.0, 1.0], "id": 5}, {"object": "x6", "name": ["__background__", "pans", "pikachu"], "weight": [1.0, 1.0, 1.0], "id": 6}, {"object": "x7", "name": ["__background__", "pans", "pikachu"], "weight": [1.0, 1.0, 1.0], "id": 7}, {"object": "x8", "name": ["__background__", "pans", "pikachu"], "weight": [1.0, 1.0, 1.0], "id": 8}, {"name": ["worn", "mounted"], "weight": [0.9971530557574306, 0.9967704305465364], "id": 9}, {"name": ["posing"], "weight": [0.9967301156817663], "id": 10}, {"name": ["bottom"], "weight": [1.0], "id": 11}, {"name": ["right"], "weight": [1.0], "id": 12}, {"name": ["top"], "weight": [1.0], "id": 13}, {"name": ["right"], "weight": [1.0], "id": 14}, {"name": ["bottom"], "weight": [1.0], "id": 15}, {"name": ["right"], "weight": [1.0], "id": 16}, {"name": ["top"], "weight": [1.0], "id": 17}, {"name": ["right"], "weight": [1.0], "id": 18}, {"name": ["bottom"], "weight": [1.0], "id": 19}, {"name": ["right"], "weight": [1.0], "id": 20}, {"name": ["bottom"], "weight": [1.0], "id": 21}, {"name": ["left"], "weight": [1.0], "id": 22}, {"name": ["bottom"], "weight": [1.0], "id": 23}, {"name": ["left"], "weight": [1.0], "id": 24}, {"name": ["bottom"], "weight": [1.0], "id": 25}, {"name": ["left"], "weight": [1.0], "id": 26}, {"name": ["bottom"], "weight": [1.0], "id": 27}, {"name": ["left"], "weight": [1.0], "id": 28}], "links": [{"id": 3, "name": ["with", "hanging in", "hitting"], "weight": [0.3354297499954829, 0.3323099088424181, 0.332260341162099], "source": 0, "target": 3}, {"id": 9, "name": ["has property"], "weight": [1.0], "source": 0, "target": 9}, {"id": 10, "name": ["has activity"], "weight": [1.0], "source": 0, "target": 10}, {"id": 11, "name": ["has vposition"], "weight": [1.0], "source": 0, "target": 11}, {"id": 12, "name": ["has hposition"], "weight": [1.0], "source": 0, "target": 12}, {"id": 13, "name": ["has vposition"], "weight": [1.0], "source": 1, "target": 13}, {"id": 14, "name": ["has hposition"], "weight": [1.0], "source": 1, "target": 14}, {"id": 3, "name": ["tossing", "driving on", "on top of"], "weight": [0.3367081830109095, 0.3322624660552406, 0.3310293509338499], "source": 2, "target": 3}, {"id": 15, "name": ["has vposition"], "weight": [1.0], "source": 2, "target": 15}, {"id": 16, "name": ["has hposition"], "weight": [1.0], "source": 2, "target": 16}, {"id": 3, "name": ["entering", "walking with", "sleeping in"], "weight": [0.33388365027019157, 0.33306960348409426, 0.3330467462457142], "source": 3, "target": 3}, {"id": 2, "name": ["leaning against", "skiing in", "entering"], "weight": [0.33365266793517273, 0.3332715808661408, 0.3330757511986865], "source": 3, "target": 2}, {"id": 8, "name": ["plugged into", "tied around", "chasing"], "weight": [0.33557264847484364, 0.33529380577849527, 0.3291335457466611], "source": 3, "target": 8}, {"id": 4, "name": ["facing", "enclosing", "cooking"], "weight": [0.3340424392102193, 0.334021224681507, 0.3319363361082737], "source": 3, "target": 4}, {"id": 17, "name": ["has vposition"], "weight": [1.0], "source": 3, "target": 17}, {"id": 18, "name": ["has hposition"], "weight": [1.0], "source": 3, "target": 18}, {"name": ["reverse with", "reverse hanging in", "reverse hitting"], "id": 0, "weight": [0.3354297499954829, 0.3323099088424181, 0.332260341162099], "source": 3, "target": 0}, {"id": 3, "name": ["growing behind", "standing on", "grabbing"], "weight": [0.3348238879146782, 0.3335289346130995, 0.33164717747222233], "source": 4, "target": 3}, {"id": 19, "name": ["has vposition"], "weight": [1.0], "source": 4, "target": 19}, {"id": 20, "name": ["has hposition"], "weight": [1.0], "source": 4, "target": 20}, {"id": 21, "name": ["has vposition"], "weight": [1.0], "source": 5, "target": 21}, {"id": 22, "name": ["has hposition"], "weight": [1.0], "source": 5, "target": 22}, {"id": 23, "name": ["has vposition"], "weight": [1.0], "source": 6, "target": 23}, {"id": 24, "name": ["has hposition"], "weight": [1.0], "source": 6, "target": 24}, {"id": 25, "name": ["has vposition"], "weight": [1.0], "source": 7, "target": 25}, {"id": 26, "name": ["has hposition"], "weight": [1.0], "source": 7, "target": 26}, {"id": 3, "name": ["topped with", "floating in", "traveling on"], "weight": [0.33451379514814744, 0.3331069329576737, 0.33237927189417876], "source": 8, "target": 3}, {"id": 27, "name": ["has vposition"], "weight": [1.0], "source": 8, "target": 27}, {"id": 28, "name": ["has hposition"], "weight": [1.0], "source": 8, "target": 28}, {"name": ["reverse has property"], "id": 0, "weight": [1.0], "source": 9, "target": 0}, {"name": ["reverse has activity"], "id": 0, "weight": [1.0], "source": 10, "target": 0}, {"name": ["reverse has vposition"], "id": 0, "weight": [1.0], "source": 11, "target": 0}, {"name": ["reverse has hposition"], "id": 0, "weight": [1.0], "source": 12, "target": 0}, {"name": ["reverse has vposition"], "id": 1, "weight": [1.0], "source": 13, "target": 1}, {"name": ["reverse has hposition"], "id": 1, "weight": [1.0], "source": 14, "target": 1}, {"name": ["reverse has vposition"], "id": 2, "weight": [1.0], "source": 15, "target": 2}, {"name": ["reverse has hposition"], "id": 2, "weight": [1.0], "source": 16, "target": 2}, {"name": ["reverse has vposition"], "id": 3, "weight": [1.0], "source": 17, "target": 3}, {"name": ["reverse has hposition"], "id": 3, "weight": [1.0], "source": 18, "target": 3}, {"name": ["reverse has vposition"], "id": 4, "weight": [1.0], "source": 19, "target": 4}, {"name": ["reverse has hposition"], "id": 4, "weight": [1.0], "source": 20, "target": 4}, {"name": ["reverse has vposition"], "id": 5, "weight": [1.0], "source": 21, "target": 5}, {"name": ["reverse has hposition"], "id": 5, "weight": [1.0], "source": 22, "target": 5}, {"name": ["reverse has vposition"], "id": 6, "weight": [1.0], "source": 23, "target": 6}, {"name": ["reverse has hposition"], "id": 6, "weight": [1.0], "source": 24, "target": 6}, {"name": ["reverse has vposition"], "id": 7, "weight": [1.0], "source": 25, "target": 7}, {"name": ["reverse has hposition"], "id": 7, "weight": [1.0], "source": 26, "target": 7}, {"name": ["reverse has vposition"], "id": 8, "weight": [1.0], "source": 27, "target": 8}, {"name": ["reverse has hposition"], "id": 8, "weight": [1.0], "source": 28, "target": 8}]}