{"directed": true, "multigraph": false, "graph": {}, "nodes": [{"object": "x0", "name": ["__background__", "pans", "pikachu"], "weight": [1.0, 1.0, 1.0], "id": 0}, {"object": "x1", "name": ["__background__", "pans", "pikachu"], "weight": [1.0, 1.0, 1.0], "id": 1}, {"object": "x2", "name": ["__background__", "pans", "pikachu"], "weight": [1.0, 1.0, 1.0], "id": 2}, {"object": "x3", "name": ["__background__", "pans", "pikachu"], "weight": [1.0, 1.0, 1.0], "id": 3}, {"object": "x4", "name": ["__background__", "pans", "pikachu"], "weight": [1.0, 1.0, 1.0], "id": 4}, {"object": "x5", "name": ["__background__", "pans", "pikachu"], "weight": [1.0, 1.0, 1.0], "id": 5}, {"object": "x6", "name": ["__background__", "pans", "pikachu"], "weight": [1.0, 1.0, 1.0], "id": 6}, {"object": "x7", "name": ["__background__", "pans", "pikachu"], "weight": [1.0, 1.0, 1.0], "id": 7}, {"object": "x8", "name": ["__background__", "pans", "pikachu"], "weight": [1.0, 1.0, 1.0], "id": 8}, {"object": "x9", "name": ["__background__", "pans", "pikachu"], "weight": [1.0, 1.0, 1.0], "id": 9}, {"object": "x10", "name": ["__background__", "pans", "pikachu"], "weight": [1.0, 1.0, 1.0], "id": 10}, {"object": "x11", "name": ["__background__", "pans", "pikachu"], "weight": [1.0, 1.0, 1.0], "id": 11}, {"object": "x12", "name": ["__background__", "pans", "pikachu"], "weight": [1.0, 1.0, 1.0], "id": 12}, {"object": "x13", "name": ["__background__", "pans", "pikachu"], "weight": [1.0, 1.0, 1.0], "id": 13}, {"object": "x14", "name": ["__background__", "pans", "pikachu"], "weight": [1.0, 1.0, 1.0], "id": 14}, {"object": "x15", "name": ["__background__", "pans", "pikachu"], "weight": [1.0, 1.0, 1.0], "id": 15}, {"object": "x16", "name": ["__background__", "pans", "pikachu"], "weight": [1.0, 1.0, 1.0], "id": 16}, {"name": ["sprinkled", "collared"], "weight": [0.999810054542892, 0.9966855723502858], "id": 17}, {"name": ["driving"], "weight": [0.9992300209120063], "id": 18}, {"name": ["round"], "weight": [0.9974504776657608], "id": 19}, {"name": ["top"], "weight": [1.0], "id": 20}, {"name": ["right"], "weight": [1.0], "id": 21}, {"name": ["bottom"], "weight": [1.0], "id": 22}, {"name": ["right"], "weight": [1.0], "id": 23}, {"name": ["top"], "weight": [1.0], "id": 24}, {"name": ["right"], "weight": [1.0], "id": 25}, {"name": ["top"], "weight": [1.0], "id": 26}, {"name": ["left"], "weight": [1.0], "id": 27}, {"name": ["top"], "weight": [1.0], "id": 28}, {"name": ["left"], "weight": [1.0], "id": 29}, {"name": ["bottom"], "weight": [1.0], "id": 30}, {"name": ["left"], "weight": [1.0], "id": 31}, {"name": ["bottom"], "weight": [1.0], "id": 32}, {"name": ["left"], "weight": [1.0], "id": 33}, {"name": ["top"], "weight": [1.0], "id": 34}, {"name": ["left"], "weight": [1.0], "id": 35}, {"name": ["bottom"], "weight": [1.0], "id": 36}, {"name": ["right"], "weight": [1.0], "id": 37}, {"name": ["bottom"], "weight": [1.0], "id": 38}, {"name": ["right"], "weight": [1.0], "id": 39}, {"name": ["top"], "weight": [1.0], "id": 40}, {"name": ["right"], "weight": [1.0], "id": 41}, {"name": ["bottom"], "weight": [1.0], "id": 42}, {"name": ["left"], "weight": [1.0], "id": 43}, {"name": ["bottom"], "weight": [1.0], "id": 44}, {"name": ["right"], "weight": [1.0], "id": 45}, {"name": ["top"], "weight": [1.0], "id": 46}, {"name": ["left"], "weight": [1.0], "id": 47}, {"name": ["bottom"], "weight": [1.0], "id": 48}, {"name": ["left"], "weight": [1.0], "id": 49}, {"name": ["top"], "weight": [1.0], "id": 50}, {"name": ["right"], "weight": [1.0], "id": 51}, {"name": ["bottom"], "weight": [1.0], "id": 52}, {"name": ["right"], "weight": [1.0], "id": 53}], "links": [{"id": 17, "name": ["has property"], "weight": [1.0], "source": 0, "target": 17}, {"id": 18, "name": ["has activity"], "weight": [1.0], "source": 0, "target": 18}, {"id": 19, "name": ["has shape"], "weight": [1.0], "source": 0, "target": 19}, {"id": 20, "name": ["has vposition"], "weight": [1.0], "source": 0, "target": 20}, {"id": 21, "name": ["has hposition"], "weight": [1.0], "source": 0, "target": 21}, {"id": 22, "name": ["has vposition"], "weight": [1.0], "source": 1, "target": 22}, {"id": 23, "name": ["has hposition"], "weight": [1.0], "source": 1, "target": 23}, {"id": 3, "name": ["photographing", "approaching", "underneath"], "weight": [0.33391654171859625, 0.3330877452582753, 0.33299571302312847], "source": 2, "target": 3}, {"id": 12, "name": ["chewing", "at", "leaning against"], "weight": [0.3342613876486129, 0.3335362201403625, 0.33220239221102454], "source": 2, "target": 12}, {"id": 24, "name": ["has vposition"], "weight": [1.0], "source": 2, "target": 24}, {"id": 25, "name": ["has hposition"], "weight": [1.0], "source": 2, "target": 25}, {"name": ["reverse by", "reverse flying through", "reverse __background__"], "id": 13, "weight": [0.3342300159446467, 0.3332453932062058, 0.3325245908491476], "source": 2, "target": 13}, {"id": 16, "name": ["reaching for", "throwing", "mounted on"], "weight": [0.3337141463429361, 0.33368356193224846, 0.3326022917248154], "source": 3, "target": 16}, {"id": 7, "name": ["walking down", "attached to", "served on"], "weight": [0.33378717209060643, 0.33350453815960246, 0.3327082897497911], "source": 3, "target": 7}, {"id": 6, "name": ["connected to", "catching", "working in"], "weight": [0.33393003001184335, 0.33309555662781826, 0.33297441336033834], "source": 3, "target": 6}, {"id": 11, "name": ["floating in", "throwing", "entering"], "weight": [0.3349766290040197, 0.33354151642561947, 0.3314818545703609], "source": 3, "target": 11}, {"id": 4, "name": ["leading", "walking on", "standing at"], "weight": [0.33363725940471733, 0.3332365714231272, 0.3331261691721555], "source": 3, "target": 4}, {"id": 2, "name": ["riding on", "printed on", "flying over"], "weight": [0.33399193491152146, 0.33327614508349734, 0.3327319200049811], "source": 3, "target": 2}, {"id": 8, "name": ["making", "adjusting", "jumping over"], "weight": [0.33379756667100885, 0.333568264498196, 0.3326341688307951], "source": 3, "target": 8}, {"id": 26, "name": ["has vposition"], "weight": [1.0], "source": 3, "target": 26}, {"id": 27, "name": ["has hposition"], "weight": [1.0], "source": 3, "target": 27}, {"id": 3, "name": ["smiling at", "hanging out of", "helping"], "weight": [0.3344533208292268, 0.3331983291043536, 0.3323483500664196], "source": 4, "target": 3}, {"id": 28, "name": ["has vposition"], "weight": [1.0], "source": 4, "target": 28}, {"id": 29, "name": ["has hposition"], "weight": [1.0], "source": 4, "target": 29}, {"id": 16, "name": ["growing by", "eating in", "following"], "weight": [0.33392765766437443, 0.33345086624211473, 0.33262147609351084], "source": 5, "target": 16}, {"id": 11, "name": ["skiing on", "shining through", "on the other side of"], "weight": [0.33381208333049833, 0.33329963271430973, 0.3328882839551919], "source": 5, "target": 11}, {"id": 12, "name": ["leaning against", "walking on", "bigger than"], "weight": [0.3340064660409187, 0.33303888783014013, 0.3329546461289412], "source": 5, "target": 12}, {"id": 14, "name": ["filled with", "drinking", "photographing"], "weight": [0.33373026171884773, 0.3333959011578414, 0.33287383712331087], "source": 5, "target": 14}, {"id": 30, "name": ["has vposition"], "weight": [1.0], "source": 5, "target": 30}, {"id": 31, "name": ["has hposition"], "weight": [1.0], "source": 5, "target": 31}, {"id": 3, "name": ["resting on", "coming out of", "lying on"], "weight": [0.33577673748078135, 0.3331360336565361, 0.3310872288626825], "source": 6, "target": 3}, {"id": 11, "name": ["walking towards", "tossing", "selling"], "weight": [0.336015964047718, 0.33272163665445625, 0.33126239929782575], "source": 6, "target": 11}, {"id": 32, "name": ["has vposition"], "weight": [1.0], "source": 6, "target": 32}, {"id": 33, "name": ["has hposition"], "weight": [1.0], "source": 6, "target": 33}, {"id": 34, "name": ["has vposition"], "weight": [1.0], "source": 7, "target": 34}, {"id": 35, "name": ["has hposition"], "weight": [1.0], "source": 7, "target": 35}, {"name": ["reverse walking down", "reverse attached to", "reverse served on"], "id": 3, "weight": [0.33378717209060643, 0.33350453815960246, 0.3327082897497911], "source": 7, "target": 3}, {"id": 11, "name": ["near", "riding in", "hanging off"], "weight": [0.3344514245791649, 0.334224473064053, 0.33132410235678217], "source": 8, "target": 11}, {"id": 36, "name": ["has vposition"], "weight": [1.0], "source": 8, "target": 36}, {"id": 37, "name": ["has hposition"], "weight": [1.0], "source": 8, "target": 37}, {"name": ["reverse making", "reverse adjusting", "reverse jumping over"], "id": 3, "weight": [0.33379756667100885, 0.333568264498196, 0.3326341688307951], "source": 8, "target": 3}, {"id": 12, "name": ["flying above", "parked at", "pulling"], "weight": [0.3351081477705342, 0.3325392418996992, 0.33235261032976654], "source": 9, "target": 12}, {"id": 38, "name": ["has vposition"], "weight": [1.0], "source": 9, "target": 38}, {"id": 39, "name": ["has hposition"], "weight": [1.0], "source": 9, "target": 39}, {"id": 15, "name": ["trying to catch", "eating from", "driving down"], "weight": [0.33388860019692596, 0.33370096103713315, 0.332410438765941], "source": 10, "target": 15}, {"id": 40, "name": ["has vposition"], "weight": [1.0], "source": 10, "target": 40}, {"id": 41, "name": ["has hposition"], "weight": [1.0], "source": 10, "target": 41}, {"id": 3, "name": ["cooking", "with", "looking in"], "weight": [0.3340650830873118, 0.3335119175255556, 0.33242299938713266], "source": 11, "target": 3}, {"id": 6, "name": ["licking", "walking up", "slicing"], "weight": [0.33463866670801473, 0.3337909257769423, 0.3315704075150429], "source": 11, "target": 6}, {"id": 8, "name": ["reflected in", "sitting around", "sitting on top of"], "weight": [0.33462514890416656, 0.33315651134304325, 0.33221833975279025], "source": 11, "target": 8}, {"id": 5, "name": ["washing", "skating on", "scattered on"], "weight": [0.33357550526847324, 0.3333131599736598, 0.333111334757867], "source": 11, "target": 5}, {"id": 42, "name": ["has vposition"], "weight": [1.0], "source": 11, "target": 42}, {"id": 43, "name": ["has hposition"], "weight": [1.0], "source": 11, "target": 43}, {"id": 9, "name": ["grazing on", "under", "looking out"], "weight": [0.33585849735662154, 0.33215128182403564, 0.3319902208193429], "source": 12, "target": 9}, {"id": 2, "name": ["parked by", "grazing on", "walking in"], "weight": [0.33394906739485153, 0.3333774298161358, 0.3326735027890127], "source": 12, "target": 2}, {"id": 5, "name": ["grazing on", "carrying", "beneath"], "weight": [0.3372335271203442, 0.3328691150270317, 0.329897357852624], "source": 12, "target": 5}, {"id": 44, "name": ["has vposition"], "weight": [1.0], "source": 12, "target": 44}, {"id": 45, "name": ["has hposition"], "weight": [1.0], "source": 12, "target": 45}, {"id": 2, "name": ["by", "flying through", "__background__"], "weight": [0.3342300159446467, 0.3332453932062058, 0.3325245908491476], "source": 13, "target": 2}, {"id": 46, "name": ["has vposition"], "weight": [1.0], "source": 13, "target": 46}, {"id": 47, "name": ["has hposition"], "weight": [1.0], "source": 13, "target": 47}, {"id": 5, "name": ["walking next to", "walking behind", "full of"], "weight": [0.33377446217093465, 0.3335734962217766, 0.3326520416072887], "source": 14, "target": 5}, {"id": 48, "name": ["has vposition"], "weight": [1.0], "source": 14, "target": 48}, {"id": 49, "name": ["has hposition"], "weight": [1.0], "source": 14, "target": 49}, {"id": 10, "name": ["standing behind", "working in", "playing"], "weight": [0.3345833395789491, 0.33286764790747625, 0.3325490125135746], "source": 15, "target": 10}, {"id": 50, "name": ["has vposition"], "weight": [1.0], "source": 15, "target": 50}, {"id": 51, "name": ["has hposition"], "weight": [1.0], "source": 15, "target": 51}, {"id": 52, "name": ["has vposition"], "weight": [1.0], "source": 16, "target": 52}, {"id": 53, "name": ["has hposition"], "weight": [1.0], "source": 16, "target": 53}, {"name": ["reverse reaching for", "reverse throwing", "reverse mounted on"], "id": 3, "weight": [0.3337141463429361, 0.33368356193224846, 0.3326022917248154], "source": 16, "target": 3}, {"name": ["reverse growing by", "reverse eating in", "reverse following"], "id": 5, "weight": [0.33392765766437443, 0.33345086624211473, 0.33262147609351084], "source": 16, "target": 5}, {"name": ["reverse has property"], "id": 0, "weight": [1.0], "source": 17, "target": 0}, {"name": ["reverse has activity"], "id": 0, "weight": [1.0], "source": 18, "target": 0}, {"name": ["reverse has shape"], "id": 0, "weight": [1.0], "source": 19, "target": 0}, {"name": ["reverse has vposition"], "id": 0, "weight": [1.0], "source": 20, "target": 0}, {"name": ["reverse has hposition"], "id": 0, "weight": [1.0], "source": 21, "target": 0}, {"name": ["reverse has vposition"], "id": 1, "weight": [1.0], "source": 22, "target": 1}, {"name": ["reverse has hposition"], "id": 1, "weight": [1.0], "source": 23, "target": 1}, {"name": ["reverse has vposition"], "id": 2, "weight": [1.0], "source": 24, "target": 2}, {"name": ["reverse has hposition"], "id": 2, "weight": [1.0], "source": 25, "target": 2}, {"name": ["reverse has vposition"], "id": 3, "weight": [1.0], "source": 26, "target": 3}, {"name": ["reverse has hposition"], "id": 3, "weight": [1.0], "source": 27, "target": 3}, {"name": ["reverse has vposition"], "id": 4, "weight": [1.0], "source": 28, "target": 4}, {"name": ["reverse has hposition"], "id": 4, "weight": [1.0], "source": 29, "target": 4}, {"name": ["reverse has vposition"], "id": 5, "weight": [1.0], "source": 30, "target": 5}, {"name": ["reverse has hposition"], "id": 5, "weight": [1.0], "source": 31, "target": 5}, {"name": ["reverse has vposition"], "id": 6, "weight": [1.0], "source": 32, "target": 6}, {"name": ["reverse has hposition"], "id": 6, "weight": [1.0], "source": 33, "target": 6}, {"name": ["reverse has vposition"], "id": 7, "weight": [1.0], "source": 34, "target": 7}, {"name": ["reverse has hposition"], "id": 7, "weight": [1.0], "source": 35, "target": 7}, {"name": ["reverse has vposition"], "id": 8, "weight": [1.0], "source": 36, "target": 8}, {"name": ["reverse has hposition"], "id": 8, "weight": [1.0], "source": 37, "target": 8}, {"name": ["reverse has vposition"], "id": 9, "weight": [1.0], "source": 38, "target": 9}, {"name": ["reverse has hposition"], "id": 9, "weight": [1.0], "source": 39, "target": 9}, {"name": ["reverse has vposition"], "id": 10, "weight": [1.0], "source": 40, "target": 10}, {"name": ["reverse has hposition"], "id": 10, "weight": [1.0], "source": 41, "target": 10}, {"name": ["reverse has vposition"], "id": 11, "weight": [1.0], "source": 42, "target": 11}, {"name": ["reverse has hposition"], "id": 11, "weight": [1.0], "source": 43, "target": 11}, {"name": ["reverse has vposition"], "id": 12, "weight": [1.0], "source": 44, "target": 12}, {"name": ["reverse has hposition"], "id": 12, "weight": [1.0], "source": 45, "target": 12}, {"name": ["reverse has vposition"], "id": 13, "weight": [1.0], "source": 46, "target": 13}, {"name": ["reverse has hposition"], "id": 13, "weight": [1.0], "source": 47, "target": 13}, {"name": ["reverse has vposition"], "id": 14, "weight": [1.0], "source": 48, "target": 14}, {"name": ["reverse has hposition"], "id": 14, "weight": [1.0], "source": 49, "target": 14}, {"name": ["reverse has vposition"], "id": 15, "weight": [1.0], "source": 50, "target": 15}, {"name": ["reverse has hposition"], "id": 15, "weight": [1.0], "source": 51, "target": 15}, {"name": ["reverse has vposition"], "id": 16, "weight": [1.0], "source": 52, "target": 16}, {"name": ["reverse has hposition"], "id": 16, "weight": [1.0], "source": 53, "target": 16}]}