{"directed": true, "multigraph": false, "graph": {}, "nodes": [{"object": "x0", "name": ["__background__", "pans", "pikachu"], "weight": [1.0, 1.0, 1.0], "id": 0}, {"object": "x1", "name": ["__background__", "pans", "pikachu"], "weight": [1.0, 1.0, 1.0], "id": 1}, {"object": "x2", "name": ["__background__", "pans", "pikachu"], "weight": [1.0, 1.0, 1.0], "id": 2}, {"object": "x3", "name": ["__background__", "pans", "pikachu"], "weight": [1.0, 1.0, 1.0], "id": 3}, {"object": "x4", "name": ["__background__", "pans", "pikachu"], "weight": [1.0, 1.0, 1.0], "id": 4}, {"object": "x5", "name": ["__background__", "pans", "pikachu"], "weight": [1.0, 1.0, 1.0], "id": 5}, {"object": "x6", "name": ["__background__", "pans", "pikachu"], "weight": [1.0, 1.0, 1.0], "id": 6}, {"object": "x7", "name": ["__background__", "pans", "pikachu"], "weight": [1.0, 1.0, 1.0], "id": 7}, {"object": "x8", "name": ["__background__", "pans", "pikachu"], "weight": [1.0, 1.0, 1.0], "id": 8}, {"object": "x9", "name": ["__background__", "pans", "pikachu"], "weight": [1.0, 1.0, 1.0], "id": 9}, {"object": "x10", "name": ["__background__", "pans", "pikachu"], "weight": [1.0, 1.0, 1.0], "id": 10}, {"object": "x11", "name": ["__background__", "pans", "pikachu"], "weight": [1.0, 1.0, 1.0], "id": 11}, {"object": "x12", "name": ["__background__", "pans", "pikachu"], "weight": [1.0, 1.0, 1.0], "id": 12}, {"object": "x13", "name": ["__background__", "pans", "pikachu"], "weight": [1.0, 1.0, 1.0], "id": 13}, {"object": "x14", "name": ["__background__", "pans", "pikachu"], "weight": [1.0, 1.0, 1.0], "id": 14}, {"object": "x15", "name": ["__background__", "pans", "pikachu"], "weight": [1.0, 1.0, 1.0], "id": 15}, {"object": "x16", "name": ["__background__", "pans", "pikachu"], "weight": [1.0, 1.0, 1.0], "id": 16}, {"object": "x17", "name": ["__background__", "pans", "pikachu"], "weight": [1.0, 1.0, 1.0], "id": 17}, {"object": "x18", "name": ["__background__", "pans", "pikachu"], "weight": [1.0, 1.0, 1.0], "id": 18}, {"object": "x19", "name": ["__background__", "pans", "pikachu"], "weight": [1.0, 1.0, 1.0], "id": 19}, {"object": "x20", "name": ["__background__", "pans", "pikachu"], "weight": [1.0, 1.0, 1.0], "id": 20}, {"object": "x21", "name": ["__background__", "pans", "pikachu"], "weight": [1.0, 1.0, 1.0], "id": 21}, {"name": ["glossy", "ornamental"], "weight": [0.9992036416285989, 0.9980790349853307], "id": 22}, {"name": ["adidas"], "weight": [0.9986525390929711], "id": 23}, {"name": ["cardboard"], "weight": [0.9932987825274848], "id": 24}, {"name": ["bottom"], "weight": [1.0], "id": 25}, {"name": ["right"], "weight": [1.0], "id": 26}, {"name": ["bottom"], "weight": [1.0], "id": 27}, {"name": ["right"], "weight": [1.0], "id": 28}, {"name": ["bottom"], "weight": [1.0], "id": 29}, {"name": ["right"], "weight": [1.0], "id": 30}, {"name": ["bottom"], "weight": [1.0], "id": 31}, {"name": ["right"], "weight": [1.0], "id": 32}, {"name": ["bottom"], "weight": [1.0], "id": 33}, {"name": ["right"], "weight": [1.0], "id": 34}, {"name": ["bottom"], "weight": [1.0], "id": 35}, {"name": ["right"], "weight": [1.0], "id": 36}, {"name": ["bottom"], "weight": [1.0], "id": 37}, {"name": ["right"], "weight": [1.0], "id": 38}, {"name": ["bottom"], "weight": [1.0], "id": 39}, {"name": ["right"], "weight": [1.0], "id": 40}, {"name": ["bottom"], "weight": [1.0], "id": 41}, {"name": ["right"], "weight": [1.0], "id": 42}, {"name": ["bottom"], "weight": [1.0], "id": 43}, {"name": ["left"], "weight": [1.0], "id": 44}, {"name": ["bottom"], "weight": [1.0], "id": 45}, {"name": ["left"], "weight": [1.0], "id": 46}, {"name": ["bottom"], "weight": [1.0], "id": 47}, {"name": ["left"], "weight": [1.0], "id": 48}, {"name": ["bottom"], "weight": [1.0], "id": 49}, {"name": ["left"], "weight": [1.0], "id": 50}, {"name": ["top"], "weight": [1.0], "id": 51}, {"name": ["right"], "weight": [1.0], "id": 52}, {"name": ["top"], "weight": [1.0], "id": 53}, {"name": ["right"], "weight": [1.0], "id": 54}, {"name": ["top"], "weight": [1.0], "id": 55}, {"name": ["left"], "weight": [1.0], "id": 56}, {"name": ["bottom"], "weight": [1.0], "id": 57}, {"name": ["right"], "weight": [1.0], "id": 58}, {"name": ["bottom"], "weight": [1.0], "id": 59}, {"name": ["right"], "weight": [1.0], "id": 60}, {"name": ["top"], "weight": [1.0], "id": 61}, {"name": ["left"], "weight": [1.0], "id": 62}, {"name": ["top"], "weight": [1.0], "id": 63}, {"name": ["right"], "weight": [1.0], "id": 64}, {"name": ["bottom"], "weight": [1.0], "id": 65}, {"name": ["left"], "weight": [1.0], "id": 66}, {"name": ["bottom"], "weight": [1.0], "id": 67}, {"name": ["right"], "weight": [1.0], "id": 68}], "links": [{"id": 17, "name": ["walking in", "seen through", "leaving"], "weight": [0.3345477396463533, 0.3337320530636815, 0.33172020728996515], "source": 0, "target": 17}, {"id": 1, "name": ["photographing", "traveling down", "brushing"], "weight": [0.33364480009905856, 0.3332276268268618, 0.33312757307407964], "source": 0, "target": 1}, {"id": 22, "name": ["has property"], "weight": [1.0], "source": 0, "target": 22}, {"id": 23, "name": ["has company"], "weight": [1.0], "source": 0, "target": 23}, {"id": 24, "name": ["has material"], "weight": [1.0], "source": 0, "target": 24}, {"id": 25, "name": ["has vposition"], "weight": [1.0], "source": 0, "target": 25}, {"id": 26, "name": ["has hposition"], "weight": [1.0], "source": 0, "target": 26}, {"id": 17, "name": ["flying above", "pointing at", "brushing"], "weight": [0.33387408868788077, 0.33370146558688774, 0.33242444572523155], "source": 1, "target": 17}, {"id": 1, "name": ["walking toward", "walking across", "posing with"], "weight": [0.33409290718460016, 0.33323688379417354, 0.33267020902122635], "source": 1, "target": 1}, {"id": 2, "name": ["walking by", "parked on", "sewn on"], "weight": [0.3337581197126086, 0.33360390248064836, 0.332637977806743], "source": 1, "target": 2}, {"id": 0, "name": ["going into", "helping", "observing"], "weight": [0.33429919792187596, 0.33414674039498293, 0.33155406168314117], "source": 1, "target": 0}, {"id": 11, "name": ["flying above", "walking to", "growing on"], "weight": [0.33415413473241146, 0.33312429229968893, 0.3327215729678996], "source": 1, "target": 11}, {"id": 27, "name": ["has vposition"], "weight": [1.0], "source": 1, "target": 27}, {"id": 28, "name": ["has hposition"], "weight": [1.0], "source": 1, "target": 28}, {"id": 17, "name": ["covered with", "swimming in", "standing by"], "weight": [0.33395056895281094, 0.3334878347166705, 0.3325615963305186], "source": 2, "target": 17}, {"id": 1, "name": ["approaching", "walking to", "floating in"], "weight": [0.33355321721787756, 0.33333735818666366, 0.3331094245954588], "source": 2, "target": 1}, {"id": 29, "name": ["has vposition"], "weight": [1.0], "source": 2, "target": 29}, {"id": 30, "name": ["has hposition"], "weight": [1.0], "source": 2, "target": 30}, {"id": 3, "name": ["worn on", "beside", "attached to"], "weight": [0.33401632599745446, 0.3334268742159962, 0.3325567997865495], "source": 3, "target": 3}, {"id": 6, "name": ["standing on", "riding in", "tied around"], "weight": [0.33381320700804595, 0.3331146032072666, 0.3330721897846875], "source": 3, "target": 6}, {"id": 7, "name": ["sitting next to", "to the right of", "contain"], "weight": [0.3338589256893815, 0.3336274756348086, 0.3325135986758098], "source": 3, "target": 7}, {"id": 21, "name": ["hang from", "drinking", "lying on"], "weight": [0.33434415922166444, 0.3328367167485886, 0.332819124029747], "source": 3, "target": 21}, {"id": 16, "name": ["coming from", "driving", "eating"], "weight": [0.33356953030424374, 0.33323501040037434, 0.33319545929538186], "source": 3, "target": 16}, {"id": 9, "name": ["blowing out", "opening", "hanging on"], "weight": [0.33402774446831546, 0.3331456227612948, 0.3328266327703899], "source": 3, "target": 9}, {"id": 31, "name": ["has vposition"], "weight": [1.0], "source": 3, "target": 31}, {"id": 32, "name": ["has hposition"], "weight": [1.0], "source": 3, "target": 32}, {"id": 9, "name": ["lying in", "seen through", "drinking from"], "weight": [0.33444503792691493, 0.3335058315563595, 0.33204913051672563], "source": 4, "target": 9}, {"id": 33, "name": ["has vposition"], "weight": [1.0], "source": 4, "target": 33}, {"id": 34, "name": ["has hposition"], "weight": [1.0], "source": 4, "target": 34}, {"id": 35, "name": ["has vposition"], "weight": [1.0], "source": 5, "target": 35}, {"id": 36, "name": ["has hposition"], "weight": [1.0], "source": 5, "target": 36}, {"id": 3, "name": ["traveling on", "flying in", "petting"], "weight": [0.3343124267741331, 0.3331902975791068, 0.33249727564676007], "source": 6, "target": 3}, {"id": 7, "name": ["growing by", "skiing in", "smelling"], "weight": [0.3342978839216808, 0.33412471708706487, 0.3315773989912543], "source": 6, "target": 7}, {"id": 9, "name": ["opening", "on the back of", "connected to"], "weight": [0.33418431564218154, 0.33405702236786833, 0.3317586619899502], "source": 6, "target": 9}, {"id": 37, "name": ["has vposition"], "weight": [1.0], "source": 6, "target": 37}, {"id": 38, "name": ["has hposition"], "weight": [1.0], "source": 6, "target": 38}, {"id": 3, "name": ["swimming in", "wading in", "underneath"], "weight": [0.334512436841882, 0.33288899542500955, 0.33259856773310836], "source": 7, "target": 3}, {"id": 9, "name": ["covering", "working in", "served on"], "weight": [0.3344676424414068, 0.3327791937348945, 0.3327531638236987], "source": 7, "target": 9}, {"id": 39, "name": ["has vposition"], "weight": [1.0], "source": 7, "target": 39}, {"id": 40, "name": ["has hposition"], "weight": [1.0], "source": 7, "target": 40}, {"name": ["reverse growing by", "reverse skiing in", "reverse smelling"], "id": 6, "weight": [0.3342978839216808, 0.33412471708706487, 0.3315773989912543], "source": 7, "target": 6}, {"id": 41, "name": ["has vposition"], "weight": [1.0], "source": 8, "target": 41}, {"id": 42, "name": ["has hposition"], "weight": [1.0], "source": 8, "target": 42}, {"id": 11, "name": ["running in", "on the bottom of", "sitting at"], "weight": [0.3340547776305607, 0.3338652173475408, 0.3320800050218984], "source": 9, "target": 11}, {"id": 16, "name": ["splashing", "drawn on", "parked at"], "weight": [0.33458471356777036, 0.3339866832161857, 0.33142860321604395], "source": 9, "target": 16}, {"id": 3, "name": ["growing from", "sleeping on", "growing behind"], "weight": [0.3348645323587939, 0.3338950394384852, 0.3312404282027209], "source": 9, "target": 3}, {"id": 7, "name": ["grazing in", "displayed on", "hanging on"], "weight": [0.33344866894940944, 0.3333881667196043, 0.3331631643309863], "source": 9, "target": 7}, {"id": 6, "name": ["sitting near", "under", "higher than"], "weight": [0.3345221190257013, 0.33296276334915126, 0.3325151176251474], "source": 9, "target": 6}, {"id": 17, "name": ["smaller than", "covering", "grazing in"], "weight": [0.3353115329369875, 0.33319146024157403, 0.3314970068214385], "source": 9, "target": 17}, {"id": 43, "name": ["has vposition"], "weight": [1.0], "source": 9, "target": 43}, {"id": 44, "name": ["has hposition"], "weight": [1.0], "source": 9, "target": 44}, {"name": ["reverse lying in", "reverse seen through", "reverse drinking from"], "id": 4, "weight": [0.33444503792691493, 0.3335058315563595, 0.33204913051672563], "source": 9, "target": 4}, {"name": ["reverse traveling on", "reverse opening", "reverse selling"], "id": 13, "weight": [0.3336843708621485, 0.3335652969345465, 0.33275033220330497], "source": 9, "target": 13}, {"id": 45, "name": ["has vposition"], "weight": [1.0], "source": 10, "target": 45}, {"id": 46, "name": ["has hposition"], "weight": [1.0], "source": 10, "target": 46}, {"id": 11, "name": ["helping", "grabbing", "looking into"], "weight": [0.3348205561125623, 0.3329610303477166, 0.3322184135397211], "source": 11, "target": 11}, {"id": 9, "name": ["hanging over", "hang from", "floating on"], "weight": [0.3336615180450905, 0.33322819551651706, 0.33311028643839247], "source": 11, "target": 9}, {"id": 1, "name": ["standing under", "opening", "photographing"], "weight": [0.33387141475904936, 0.33347507228568185, 0.33265351295526885], "source": 11, "target": 1}, {"id": 47, "name": ["has vposition"], "weight": [1.0], "source": 11, "target": 47}, {"id": 48, "name": ["has hposition"], "weight": [1.0], "source": 11, "target": 48}, {"id": 49, "name": ["has vposition"], "weight": [1.0], "source": 12, "target": 49}, {"id": 50, "name": ["has hposition"], "weight": [1.0], "source": 12, "target": 50}, {"id": 9, "name": ["traveling on", "opening", "selling"], "weight": [0.3336843708621485, 0.3335652969345465, 0.33275033220330497], "source": 13, "target": 9}, {"id": 51, "name": ["has vposition"], "weight": [1.0], "source": 13, "target": 51}, {"id": 52, "name": ["has hposition"], "weight": [1.0], "source": 13, "target": 52}, {"id": 53, "name": ["has vposition"], "weight": [1.0], "source": 14, "target": 53}, {"id": 54, "name": ["has hposition"], "weight": [1.0], "source": 14, "target": 54}, {"id": 55, "name": ["has vposition"], "weight": [1.0], "source": 15, "target": 55}, {"id": 56, "name": ["has hposition"], "weight": [1.0], "source": 15, "target": 56}, {"id": 3, "name": ["chained to", "jumping on", "flying through"], "weight": [0.33416701814983263, 0.33357262692090917, 0.3322603549292582], "source": 16, "target": 3}, {"id": 9, "name": ["holding onto", "drinking from", "sitting under"], "weight": [0.3346402064124333, 0.3332224965601876, 0.3321372970273791], "source": 16, "target": 9}, {"id": 57, "name": ["has vposition"], "weight": [1.0], "source": 16, "target": 57}, {"id": 58, "name": ["has hposition"], "weight": [1.0], "source": 16, "target": 58}, {"id": 1, "name": ["chewing", "worn around", "reading"], "weight": [0.33493914405282077, 0.3334524193503153, 0.33160843659686384], "source": 17, "target": 1}, {"id": 2, "name": ["herding", "hanging on", "growing in"], "weight": [0.33468523251335186, 0.3327388255589127, 0.3325759419277353], "source": 17, "target": 2}, {"id": 0, "name": ["standing around", "looking over", "worn around"], "weight": [0.33341976442244975, 0.3333525790115146, 0.3332276565660357], "source": 17, "target": 0}, {"id": 9, "name": ["about to hit", "pulled by", "feeding"], "weight": [0.3342293005171632, 0.33371214086799433, 0.3320585586148424], "source": 17, "target": 9}, {"id": 18, "name": ["stacked on", "sleeping on", "leaning over"], "weight": [0.3339605930507198, 0.33303341950430204, 0.3330059874449782], "source": 17, "target": 18}, {"id": 59, "name": ["has vposition"], "weight": [1.0], "source": 17, "target": 59}, {"id": 60, "name": ["has hposition"], "weight": [1.0], "source": 17, "target": 60}, {"id": 61, "name": ["has vposition"], "weight": [1.0], "source": 18, "target": 61}, {"id": 62, "name": ["has hposition"], "weight": [1.0], "source": 18, "target": 62}, {"name": ["reverse stacked on", "reverse sleeping on", "reverse leaning over"], "id": 17, "weight": [0.3339605930507198, 0.33303341950430204, 0.3330059874449782], "source": 18, "target": 17}, {"id": 63, "name": ["has vposition"], "weight": [1.0], "source": 19, "target": 63}, {"id": 64, "name": ["has hposition"], "weight": [1.0], "source": 19, "target": 64}, {"id": 21, "name": ["bigger than", "pulled by", "sitting under"], "weight": [0.3343820592530964, 0.33315888789751397, 0.3324590528493896], "source": 20, "target": 21}, {"id": 65, "name": ["has vposition"], "weight": [1.0], "source": 20, "target": 65}, {"id": 66, "name": ["has hposition"], "weight": [1.0], "source": 20, "target": 66}, {"id": 20, "name": ["taller than", "parked along", "underneath"], "weight": [0.3336339726671486, 0.3331883778529982, 0.33317764947985323], "source": 21, "target": 20}, {"id": 3, "name": ["in front of", "surrounded by", "lying inside"], "weight": [0.33407032428549405, 0.33316997094814965, 0.3327597047663563], "source": 21, "target": 3}, {"id": 67, "name": ["has vposition"], "weight": [1.0], "source": 21, "target": 67}, {"id": 68, "name": ["has hposition"], "weight": [1.0], "source": 21, "target": 68}, {"name": ["reverse has property"], "id": 0, "weight": [1.0], "source": 22, "target": 0}, {"name": ["reverse has company"], "id": 0, "weight": [1.0], "source": 23, "target": 0}, {"name": ["reverse has material"], "id": 0, "weight": [1.0], "source": 24, "target": 0}, {"name": ["reverse has vposition"], "id": 0, "weight": [1.0], "source": 25, "target": 0}, {"name": ["reverse has hposition"], "id": 0, "weight": [1.0], "source": 26, "target": 0}, {"name": ["reverse has vposition"], "id": 1, "weight": [1.0], "source": 27, "target": 1}, {"name": ["reverse has hposition"], "id": 1, "weight": [1.0], "source": 28, "target": 1}, {"name": ["reverse has vposition"], "id": 2, "weight": [1.0], "source": 29, "target": 2}, {"name": ["reverse has hposition"], "id": 2, "weight": [1.0], "source": 30, "target": 2}, {"name": ["reverse has vposition"], "id": 3, "weight": [1.0], "source": 31, "target": 3}, {"name": ["reverse has hposition"], "id": 3, "weight": [1.0], "source": 32, "target": 3}, {"name": ["reverse has vposition"], "id": 4, "weight": [1.0], "source": 33, "target": 4}, {"name": ["reverse has hposition"], "id": 4, "weight": [1.0], "source": 34, "target": 4}, {"name": ["reverse has vposition"], "id": 5, "weight": [1.0], "source": 35, "target": 5}, {"name": ["reverse has hposition"], "id": 5, "weight": [1.0], "source": 36, "target": 5}, {"name": ["reverse has vposition"], "id": 6, "weight": [1.0], "source": 37, "target": 6}, {"name": ["reverse has hposition"], "id": 6, "weight": [1.0], "source": 38, "target": 6}, {"name": ["reverse has vposition"], "id": 7, "weight": [1.0], "source": 39, "target": 7}, {"name": ["reverse has hposition"], "id": 7, "weight": [1.0], "source": 40, "target": 7}, {"name": ["reverse has vposition"], "id": 8, "weight": [1.0], "source": 41, "target": 8}, {"name": ["reverse has hposition"], "id": 8, "weight": [1.0], "source": 42, "target": 8}, {"name": ["reverse has vposition"], "id": 9, "weight": [1.0], "source": 43, "target": 9}, {"name": ["reverse has hposition"], "id": 9, "weight": [1.0], "source": 44, "target": 9}, {"name": ["reverse has vposition"], "id": 10, "weight": [1.0], "source": 45, "target": 10}, {"name": ["reverse has hposition"], "id": 10, "weight": [1.0], "source": 46, "target": 10}, {"name": ["reverse has vposition"], "id": 11, "weight": [1.0], "source": 47, "target": 11}, {"name": ["reverse has hposition"], "id": 11, "weight": [1.0], "source": 48, "target": 11}, {"name": ["reverse has vposition"], "id": 12, "weight": [1.0], "source": 49, "target": 12}, {"name": ["reverse has hposition"], "id": 12, "weight": [1.0], "source": 50, "target": 12}, {"name": ["reverse has vposition"], "id": 13, "weight": [1.0], "source": 51, "target": 13}, {"name": ["reverse has hposition"], "id": 13, "weight": [1.0], "source": 52, "target": 13}, {"name": ["reverse has vposition"], "id": 14, "weight": [1.0], "source": 53, "target": 14}, {"name": ["reverse has hposition"], "id": 14, "weight": [1.0], "source": 54, "target": 14}, {"name": ["reverse has vposition"], "id": 15, "weight": [1.0], "source": 55, "target": 15}, {"name": ["reverse has hposition"], "id": 15, "weight": [1.0], "source": 56, "target": 15}, {"name": ["reverse has vposition"], "id": 16, "weight": [1.0], "source": 57, "target": 16}, {"name": ["reverse has hposition"], "id": 16, "weight": [1.0], "source": 58, "target": 16}, {"name": ["reverse has vposition"], "id": 17, "weight": [1.0], "source": 59, "target": 17}, {"name": ["reverse has hposition"], "id": 17, "weight": [1.0], "source": 60, "target": 17}, {"name": ["reverse has vposition"], "id": 18, "weight": [1.0], "source": 61, "target": 18}, {"name": ["reverse has hposition"], "id": 18, "weight": [1.0], "source": 62, "target": 18}, {"name": ["reverse has vposition"], "id": 19, "weight": [1.0], "source": 63, "target": 19}, {"name": ["reverse has hposition"], "id": 19, "weight": [1.0], "source": 64, "target": 19}, {"name": ["reverse has vposition"], "id": 20, "weight": [1.0], "source": 65, "target": 20}, {"name": ["reverse has hposition"], "id": 20, "weight": [1.0], "source": 66, "target": 20}, {"name": ["reverse has vposition"], "id": 21, "weight": [1.0], "source": 67, "target": 21}, {"name": ["reverse has hposition"], "id": 21, "weight": [1.0], "source": 68, "target": 21}]}