{"directed": true, "multigraph": false, "graph": {}, "nodes": [{"object": "x0", "name": ["__background__", "pans", "pikachu"], "weight": [1.0, 1.0, 1.0], "id": 0}, {"object": "x1", "name": ["__background__", "pans", "pikachu"], "weight": [1.0, 1.0, 1.0], "id": 1}, {"object": "x2", "name": ["__background__", "pans", "pikachu"], "weight": [1.0, 1.0, 1.0], "id": 2}, {"object": "x3", "name": ["__background__", "pans", "pikachu"], "weight": [1.0, 1.0, 1.0], "id": 3}, {"object": "x4", "name": ["__background__", "pans", "pikachu"], "weight": [1.0, 1.0, 1.0], "id": 4}, {"object": "x5", "name": ["__background__", "pans", "pikachu"], "weight": [1.0, 1.0, 1.0], "id": 5}, {"object": "x6", "name": ["__background__", "pans", "pikachu"], "weight": [1.0, 1.0, 1.0], "id": 6}, {"object": "x7", "name": ["__background__", "pans", "pikachu"], "weight": [1.0, 1.0, 1.0], "id": 7}, {"object": "x8", "name": ["__background__", "pans", "pikachu"], "weight": [1.0, 1.0, 1.0], "id": 8}, {"object": "x9", "name": ["__background__", "pans", "pikachu"], "weight": [1.0, 1.0, 1.0], "id": 9}, {"object": "x10", "name": ["__background__", "pans", "pikachu"], "weight": [1.0, 1.0, 1.0], "id": 10}, {"object": "x11", "name": ["__background__", "pans", "pikachu"], "weight": [1.0, 1.0, 1.0], "id": 11}, {"object": "x12", "name": ["__background__", "pans", "pikachu"], "weight": [1.0, 1.0, 1.0], "id": 12}, {"object": "x13", "name": ["__background__", "pans", "pikachu"], "weight": [1.0, 1.0, 1.0], "id": 13}, {"object": "x14", "name": ["__background__", "pans", "pikachu"], "weight": [1.0, 1.0, 1.0], "id": 14}, {"object": "x15", "name": ["__background__", "pans", "pikachu"], "weight": [1.0, 1.0, 1.0], "id": 15}, {"object": "x16", "name": ["__background__", "pans", "pikachu"], "weight": [1.0, 1.0, 1.0], "id": 16}, {"object": "x17", "name": ["__background__", "pans", "pikachu"], "weight": [1.0, 1.0, 1.0], "id": 17}, {"object": "x18", "name": ["__background__", "pans", "pikachu"], "weight": [1.0, 1.0, 1.0], "id": 18}, {"object": "x19", "name": ["__background__", "pans", "pikachu"], "weight": [1.0, 1.0, 1.0], "id": 19}, {"object": "x20", "name": ["__background__", "pans", "pikachu"], "weight": [1.0, 1.0, 1.0], "id": 20}, {"object": "x21", "name": ["__background__", "pans", "pikachu"], "weight": [1.0, 1.0, 1.0], "id": 21}, {"object": "x22", "name": ["__background__", "pans", "pikachu"], "weight": [1.0, 1.0, 1.0], "id": 22}, {"name": ["cream colored"], "weight": [0.9990978530181839], "id": 23}, {"name": ["tiled", "artificial"], "weight": [0.9942473123163237, 0.9895713587502712], "id": 24}, {"name": ["fat"], "weight": [0.9992315064378373], "id": 25}, {"name": ["top"], "weight": [1.0], "id": 26}, {"name": ["left"], "weight": [1.0], "id": 27}, {"name": ["bottom"], "weight": [1.0], "id": 28}, {"name": ["left"], "weight": [1.0], "id": 29}, {"name": ["bottom"], "weight": [1.0], "id": 30}, {"name": ["left"], "weight": [1.0], "id": 31}, {"name": ["top"], "weight": [1.0], "id": 32}, {"name": ["right"], "weight": [1.0], "id": 33}, {"name": ["top"], "weight": [1.0], "id": 34}, {"name": ["right"], "weight": [1.0], "id": 35}, {"name": ["top"], "weight": [1.0], "id": 36}, {"name": ["left"], "weight": [1.0], "id": 37}, {"name": ["top"], "weight": [1.0], "id": 38}, {"name": ["right"], "weight": [1.0], "id": 39}, {"name": ["top"], "weight": [1.0], "id": 40}, {"name": ["right"], "weight": [1.0], "id": 41}, {"name": ["bottom"], "weight": [1.0], "id": 42}, {"name": ["left"], "weight": [1.0], "id": 43}, {"name": ["bottom"], "weight": [1.0], "id": 44}, {"name": ["right"], "weight": [1.0], "id": 45}, {"name": ["top"], "weight": [1.0], "id": 46}, {"name": ["right"], "weight": [1.0], "id": 47}, {"name": ["bottom"], "weight": [1.0], "id": 48}, {"name": ["right"], "weight": [1.0], "id": 49}, {"name": ["top"], "weight": [1.0], "id": 50}, {"name": ["right"], "weight": [1.0], "id": 51}, {"name": ["bottom"], "weight": [1.0], "id": 52}, {"name": ["left"], "weight": [1.0], "id": 53}, {"name": ["top"], "weight": [1.0], "id": 54}, {"name": ["right"], "weight": [1.0], "id": 55}, {"name": ["top"], "weight": [1.0], "id": 56}, {"name": ["right"], "weight": [1.0], "id": 57}, {"name": ["bottom"], "weight": [1.0], "id": 58}, {"name": ["left"], "weight": [1.0], "id": 59}, {"name": ["bottom"], "weight": [1.0], "id": 60}, {"name": ["right"], "weight": [1.0], "id": 61}, {"name": ["top"], "weight": [1.0], "id": 62}, {"name": ["left"], "weight": [1.0], "id": 63}, {"name": ["top"], "weight": [1.0], "id": 64}, {"name": ["left"], "weight": [1.0], "id": 65}, {"name": ["bottom"], "weight": [1.0], "id": 66}, {"name": ["left"], "weight": [1.0], "id": 67}, {"name": ["top"], "weight": [1.0], "id": 68}, {"name": ["left"], "weight": [1.0], "id": 69}, {"name": ["top"], "weight": [1.0], "id": 70}, {"name": ["right"], "weight": [1.0], "id": 71}], "links": [{"id": 5, "name": ["typing on", "throwing", "draped over"], "weight": [0.33489035889051444, 0.3334565174263977, 0.33165312368308775], "source": 0, "target": 5}, {"id": 15, "name": ["mounted to", "tying", "on the other side of"], "weight": [0.3342728567056292, 0.33335373647755806, 0.33237340681681277], "source": 0, "target": 15}, {"id": 19, "name": ["coming down", "running through", "standing under"], "weight": [0.3337668150725824, 0.3333495135791039, 0.33288367134831376], "source": 0, "target": 19}, {"id": 23, "name": ["has color"], "weight": [1.0], "source": 0, "target": 23}, {"id": 24, "name": ["has property"], "weight": [1.0], "source": 0, "target": 24}, {"id": 25, "name": ["has fatness"], "weight": [1.0], "source": 0, "target": 25}, {"id": 26, "name": ["has vposition"], "weight": [1.0], "source": 0, "target": 26}, {"id": 27, "name": ["has hposition"], "weight": [1.0], "source": 0, "target": 27}, {"id": 8, "name": ["pushed by", "watching", "standing by"], "weight": [0.3340850201935177, 0.33313499547366726, 0.332779984332815], "source": 1, "target": 8}, {"id": 2, "name": ["hidden by", "flying through", "walking down"], "weight": [0.33529481401973477, 0.3325393620811033, 0.3321658238991619], "source": 1, "target": 2}, {"id": 16, "name": ["going down", "wearing", "hitting"], "weight": [0.33372390492353515, 0.33343649702617945, 0.33283959805028546], "source": 1, "target": 16}, {"id": 28, "name": ["has vposition"], "weight": [1.0], "source": 1, "target": 28}, {"id": 29, "name": ["has hposition"], "weight": [1.0], "source": 1, "target": 29}, {"id": 1, "name": ["standing behind", "walking towards", "walking next to"], "weight": [0.334140896277774, 0.3331999446801831, 0.33265915904204285], "source": 2, "target": 1}, {"id": 17, "name": ["opening", "chasing", "lying in"], "weight": [0.3337602551182291, 0.33333951569882425, 0.3329002291829466], "source": 2, "target": 17}, {"id": 19, "name": ["parked at", "under", "hanging above"], "weight": [0.3355376261472228, 0.3325172354001009, 0.33194513845267626], "source": 2, "target": 19}, {"id": 8, "name": ["jumping off", "following", "enclosing"], "weight": [0.33380078391173074, 0.33366646442152514, 0.33253275166674406], "source": 2, "target": 8}, {"id": 15, "name": ["walking along", "served on", "parked by"], "weight": [0.3336582241990431, 0.3332448163771911, 0.3330969594237658], "source": 2, "target": 15}, {"id": 10, "name": ["on the bottom of", "going through", "stuck in"], "weight": [0.3340120915178242, 0.3330050406134319, 0.3329828678687438], "source": 2, "target": 10}, {"id": 9, "name": ["walking on", "looking into", "contain"], "weight": [0.3358749816349668, 0.3351071042307573, 0.3290179141342758], "source": 2, "target": 9}, {"id": 30, "name": ["has vposition"], "weight": [1.0], "source": 2, "target": 30}, {"id": 31, "name": ["has hposition"], "weight": [1.0], "source": 2, "target": 31}, {"id": 15, "name": ["driving down", "sprinkled on", "sitting on"], "weight": [0.33357028891764207, 0.3333585630473262, 0.3330711480350318], "source": 3, "target": 15}, {"id": 10, "name": ["splashing", "resting on", "moving"], "weight": [0.33425101970313104, 0.3329246517211549, 0.33282432857571415], "source": 3, "target": 10}, {"id": 19, "name": ["hitting", "parked along", "petting"], "weight": [0.3343727146574533, 0.33302215615372593, 0.33260512918882074], "source": 3, "target": 19}, {"id": 32, "name": ["has vposition"], "weight": [1.0], "source": 3, "target": 32}, {"id": 33, "name": ["has hposition"], "weight": [1.0], "source": 3, "target": 33}, {"name": ["reverse hanging above", "reverse bigger than", "reverse sitting at"], "id": 6, "weight": [0.3339601356209659, 0.3335881426505626, 0.33245172172847154], "source": 3, "target": 6}, {"id": 10, "name": ["in front of", "driving", "photographing"], "weight": [0.3335782519545333, 0.33323389724084324, 0.3331878508046235], "source": 4, "target": 10}, {"id": 15, "name": ["towing", "walking down", "crossing"], "weight": [0.3346932342951071, 0.33320472608548973, 0.33210203961940316], "source": 4, "target": 15}, {"id": 19, "name": ["touching", "stuck in", "parked behind"], "weight": [0.33347657329574887, 0.333344269738965, 0.3331791569652862], "source": 4, "target": 19}, {"id": 34, "name": ["has vposition"], "weight": [1.0], "source": 4, "target": 34}, {"id": 35, "name": ["has hposition"], "weight": [1.0], "source": 4, "target": 35}, {"id": 0, "name": ["hanging above", "standing on", "tossing"], "weight": [0.3350122740984185, 0.33284467213137825, 0.33214305377020326], "source": 5, "target": 0}, {"id": 10, "name": ["around", "sitting by", "looking through"], "weight": [0.33394001652297434, 0.33351410332927184, 0.3325458801477538], "source": 5, "target": 10}, {"id": 19, "name": ["walking up", "hanging in", "balancing on"], "weight": [0.33607222300375506, 0.33248022981403097, 0.331447547182214], "source": 5, "target": 19}, {"id": 8, "name": ["draped over", "sitting on top of", "on the side of"], "weight": [0.3337552500849343, 0.3333305902054449, 0.3329141597096208], "source": 5, "target": 8}, {"id": 36, "name": ["has vposition"], "weight": [1.0], "source": 5, "target": 36}, {"id": 37, "name": ["has hposition"], "weight": [1.0], "source": 5, "target": 37}, {"id": 15, "name": ["standing against", "typing on", "playing"], "weight": [0.33381577073662755, 0.3331265969663405, 0.333057632297032], "source": 6, "target": 15}, {"id": 3, "name": ["hanging above", "bigger than", "sitting at"], "weight": [0.3339601356209659, 0.3335881426505626, 0.33245172172847154], "source": 6, "target": 3}, {"id": 10, "name": ["buying", "cutting", "coming from"], "weight": [0.3346729912683574, 0.3331774000770322, 0.3321496086546104], "source": 6, "target": 10}, {"id": 38, "name": ["has vposition"], "weight": [1.0], "source": 6, "target": 38}, {"id": 39, "name": ["has hposition"], "weight": [1.0], "source": 6, "target": 39}, {"id": 15, "name": ["standing beside", "sitting in", "in between"], "weight": [0.3349752113220081, 0.33265373021334366, 0.3323710584646483], "source": 7, "target": 15}, {"id": 19, "name": ["cooking", "on the bottom of", "leading"], "weight": [0.33360099434786206, 0.33337223992113285, 0.33302676573100504], "source": 7, "target": 19}, {"id": 10, "name": ["exiting", "throwing", "walking on"], "weight": [0.334053012865578, 0.33387759269710193, 0.3320693944373201], "source": 7, "target": 10}, {"id": 40, "name": ["has vposition"], "weight": [1.0], "source": 7, "target": 40}, {"id": 41, "name": ["has hposition"], "weight": [1.0], "source": 7, "target": 41}, {"name": ["reverse splashing", "reverse scattered on", "reverse to the left of"], "id": 14, "weight": [0.3338722382256893, 0.33315604028145496, 0.33297172149285587], "source": 7, "target": 14}, {"id": 15, "name": ["stacked on", "standing behind", "sitting with"], "weight": [0.3346301089448354, 0.3330415437051548, 0.33232834735000977], "source": 8, "target": 15}, {"id": 19, "name": ["sitting at", "followed by", "surrounded by"], "weight": [0.3337077994572813, 0.33330470761867087, 0.3329874929240479], "source": 8, "target": 19}, {"id": 17, "name": ["on the other side of", "serving", "looking into"], "weight": [0.3338401166372711, 0.3331437620442252, 0.33301612131850383], "source": 8, "target": 17}, {"id": 1, "name": ["on the side of", "worn on", "falling off"], "weight": [0.333591305654223, 0.33335021278724297, 0.333058481558534], "source": 8, "target": 1}, {"id": 10, "name": ["reflecting in", "stuck on", "eating"], "weight": [0.3344959849459919, 0.3328564909112795, 0.3326475241427285], "source": 8, "target": 10}, {"id": 42, "name": ["has vposition"], "weight": [1.0], "source": 8, "target": 42}, {"id": 43, "name": ["has hposition"], "weight": [1.0], "source": 8, "target": 43}, {"name": ["reverse jumping off", "reverse following", "reverse enclosing"], "id": 2, "weight": [0.33380078391173074, 0.33366646442152514, 0.33253275166674406], "source": 8, "target": 2}, {"name": ["reverse draped over", "reverse sitting on top of", "reverse on the side of"], "id": 5, "weight": [0.3337552500849343, 0.3333305902054449, 0.3329141597096208], "source": 8, "target": 5}, {"name": ["reverse in front of", "reverse leaning on", "reverse pushing"], "id": 9, "weight": [0.3339235101526747, 0.3331696139912591, 0.3329068758560662], "source": 8, "target": 9}, {"id": 2, "name": ["talking on", "parked at", "on top of"], "weight": [0.3336568423579376, 0.33317584285158464, 0.33316731479047784], "source": 9, "target": 2}, {"id": 17, "name": ["herding", "jumping over", "boarding"], "weight": [0.3347717844486371, 0.3327706625436679, 0.33245755300769503], "source": 9, "target": 17}, {"id": 8, "name": ["in front of", "leaning on", "pushing"], "weight": [0.3339235101526747, 0.3331696139912591, 0.3329068758560662], "source": 9, "target": 8}, {"id": 10, "name": ["standing in", "photographing", "pushed by"], "weight": [0.33514374712920725, 0.3324331799205923, 0.3324230729502005], "source": 9, "target": 10}, {"id": 15, "name": ["jumping on", "covered with", "running on"], "weight": [0.3335823310055144, 0.33346970750233057, 0.3329479614921551], "source": 9, "target": 15}, {"id": 44, "name": ["has vposition"], "weight": [1.0], "source": 9, "target": 44}, {"id": 45, "name": ["has hposition"], "weight": [1.0], "source": 9, "target": 45}, {"id": 18, "name": ["displayed on", "below", "hung on"], "weight": [0.3337695242337335, 0.3333548159273616, 0.33287565983890494], "source": 10, "target": 18}, {"id": 2, "name": ["below", "leaning against", "balancing on"], "weight": [0.3335559710921611, 0.3333796315079931, 0.3330643973998458], "source": 10, "target": 2}, {"id": 15, "name": ["wading in", "looking into", "riding on"], "weight": [0.3352158566161935, 0.33255595440419516, 0.33222818897961126], "source": 10, "target": 15}, {"id": 9, "name": ["painted on", "around", "plugged into"], "weight": [0.33439552379517823, 0.3328765316343304, 0.33272794457049143], "source": 10, "target": 9}, {"id": 3, "name": ["balancing on", "contain", "sitting at"], "weight": [0.3342401053368816, 0.3337249244958743, 0.33203497016724404], "source": 10, "target": 3}, {"id": 4, "name": ["beneath", "pulled by", "riding on"], "weight": [0.334804737791697, 0.33266433948231966, 0.33253092272598334], "source": 10, "target": 4}, {"id": 6, "name": ["chasing", "lying next to", "walking toward"], "weight": [0.333761388573408, 0.33334990449273605, 0.33288870693385597], "source": 10, "target": 6}, {"id": 5, "name": ["parked on", "resting on", "parked near"], "weight": [0.33395979381918556, 0.3334391858926792, 0.3326010202881352], "source": 10, "target": 5}, {"id": 8, "name": ["photographing", "growing from", "blowing out"], "weight": [0.3345328518281289, 0.33330413953345533, 0.3321630086384158], "source": 10, "target": 8}, {"id": 7, "name": ["making", "painted on", "pulled by"], "weight": [0.33345521195642447, 0.3334462250900542, 0.3330985629535213], "source": 10, "target": 7}, {"id": 14, "name": ["working in", "full of", "standing by"], "weight": [0.3335961936851322, 0.33321950207665746, 0.3331843042382104], "source": 10, "target": 14}, {"id": 46, "name": ["has vposition"], "weight": [1.0], "source": 10, "target": 46}, {"id": 47, "name": ["has hposition"], "weight": [1.0], "source": 10, "target": 47}, {"id": 48, "name": ["has vposition"], "weight": [1.0], "source": 11, "target": 48}, {"id": 49, "name": ["has hposition"], "weight": [1.0], "source": 11, "target": 49}, {"id": 50, "name": ["has vposition"], "weight": [1.0], "source": 12, "target": 50}, {"id": 51, "name": ["has hposition"], "weight": [1.0], "source": 12, "target": 51}, {"id": 15, "name": ["pointing at", "walking through", "walking past"], "weight": [0.33419252174860814, 0.3332396880962582, 0.3325677901551336], "source": 13, "target": 15}, {"id": 19, "name": ["perched on", "about to hit", "using"], "weight": [0.33402980413109323, 0.3334864590377143, 0.3324837368311924], "source": 13, "target": 19}, {"id": 16, "name": ["drinking", "reading", "sitting behind"], "weight": [0.33469533775027954, 0.3334786380402731, 0.33182602420944735], "source": 13, "target": 16}, {"id": 52, "name": ["has vposition"], "weight": [1.0], "source": 13, "target": 52}, {"id": 53, "name": ["has hposition"], "weight": [1.0], "source": 13, "target": 53}, {"id": 15, "name": ["on the side of", "on", "__background__"], "weight": [0.33578333084050316, 0.3328481420192985, 0.3313685271401983], "source": 14, "target": 15}, {"id": 19, "name": ["observing", "grabbing", "walking to"], "weight": [0.3343390806025964, 0.33371392054020516, 0.33194699885719847], "source": 14, "target": 19}, {"id": 7, "name": ["splashing", "scattered on", "to the left of"], "weight": [0.3338722382256893, 0.33315604028145496, 0.33297172149285587], "source": 14, "target": 7}, {"id": 10, "name": ["on the bottom of", "dragging", "biting"], "weight": [0.33680855380531816, 0.33170921351866833, 0.3314822326760135], "source": 14, "target": 10}, {"id": 54, "name": ["has vposition"], "weight": [1.0], "source": 14, "target": 54}, {"id": 55, "name": ["has hposition"], "weight": [1.0], "source": 14, "target": 55}, {"id": 17, "name": ["walking behind", "talking on", "driving on"], "weight": [0.33343332100002193, 0.33339335920358115, 0.33317331979639686], "source": 15, "target": 17}, {"id": 18, "name": ["connected to", "kicking", "longer than"], "weight": [0.3341848933419778, 0.3335120965690933, 0.33230301008892893], "source": 15, "target": 18}, {"id": 10, "name": ["moving", "catching", "parked along"], "weight": [0.3334116882942864, 0.33337247933261355, 0.33321583237310004], "source": 15, "target": 10}, {"id": 14, "name": ["to the right of", "going into", "growing on"], "weight": [0.334299658542968, 0.3329600661045499, 0.3327402753524821], "source": 15, "target": 14}, {"id": 8, "name": ["washing", "displayed on", "growing along"], "weight": [0.3346402472054187, 0.33441896128483695, 0.3309407915097444], "source": 15, "target": 8}, {"id": 9, "name": ["carrying", "standing in front of", "by"], "weight": [0.3343321174782553, 0.333401947646225, 0.33226593487551964], "source": 15, "target": 9}, {"id": 4, "name": ["lying on", "skiing in", "pouring"], "weight": [0.3344671953617286, 0.332913912177472, 0.3326188924607994], "source": 15, "target": 4}, {"id": 6, "name": ["on the edge of", "making", "walking down"], "weight": [0.33354794334677285, 0.33345489558436064, 0.33299716106886645], "source": 15, "target": 6}, {"id": 3, "name": ["drinking from", "longer than", "to the left of"], "weight": [0.33400789814496007, 0.33313458891181646, 0.3328575129432234], "source": 15, "target": 3}, {"id": 16, "name": ["on the edge of", "sprinkled on", "parked by"], "weight": [0.3347941977232243, 0.3329181895450816, 0.3322876127316942], "source": 15, "target": 16}, {"id": 13, "name": ["with", "worn around", "herding"], "weight": [0.3334864742159496, 0.33340466274639424, 0.33310886303765624], "source": 15, "target": 13}, {"id": 2, "name": ["washing", "wrapped around", "boarding"], "weight": [0.33343021603340106, 0.33332621944582697, 0.33324356452077203], "source": 15, "target": 2}, {"id": 0, "name": ["walking toward", "parked at", "posing with"], "weight": [0.33438426923650394, 0.3332024628213981, 0.332413267942098], "source": 15, "target": 0}, {"id": 19, "name": ["facing", "lying in", "tied around"], "weight": [0.33534360582831696, 0.33294427374776153, 0.3317121204239215], "source": 15, "target": 19}, {"id": 7, "name": ["boarding", "walking on", "going through"], "weight": [0.33383090168782276, 0.33353596719703243, 0.3326331311151447], "source": 15, "target": 7}, {"id": 56, "name": ["has vposition"], "weight": [1.0], "source": 15, "target": 56}, {"id": 57, "name": ["has hposition"], "weight": [1.0], "source": 15, "target": 57}, {"id": 13, "name": ["sitting near", "looking at", "bigger than"], "weight": [0.3340269118442735, 0.33300246192360894, 0.3329706262321175], "source": 16, "target": 13}, {"id": 15, "name": ["leaning over", "sleeping in", "sitting by"], "weight": [0.33410397914666684, 0.33304903840740707, 0.3328469824459261], "source": 16, "target": 15}, {"id": 1, "name": ["sitting by", "lying in", "taller than"], "weight": [0.3337522876511588, 0.33331816173442824, 0.3329295506144129], "source": 16, "target": 1}, {"id": 58, "name": ["has vposition"], "weight": [1.0], "source": 16, "target": 58}, {"id": 59, "name": ["has hposition"], "weight": [1.0], "source": 16, "target": 59}, {"id": 15, "name": ["looking over", "stuck on", "opening"], "weight": [0.33469295565267776, 0.3334920137471483, 0.3318150306001739], "source": 17, "target": 15}, {"id": 2, "name": ["skiing in", "wading in", "preparing"], "weight": [0.3357798247663561, 0.33271408389053436, 0.33150609134310954], "source": 17, "target": 2}, {"id": 8, "name": ["flying above", "swinging", "smiling at"], "weight": [0.33403619815067925, 0.3329841300097904, 0.3329796718395304], "source": 17, "target": 8}, {"id": 18, "name": ["throwing", "worn around", "standing in front of"], "weight": [0.3350016710914599, 0.3330227811123495, 0.33197554779619065], "source": 17, "target": 18}, {"id": 9, "name": ["flying over", "buying", "standing at"], "weight": [0.3350201468653007, 0.3332079169740669, 0.33177193616063233], "source": 17, "target": 9}, {"id": 60, "name": ["has vposition"], "weight": [1.0], "source": 17, "target": 60}, {"id": 61, "name": ["has hposition"], "weight": [1.0], "source": 17, "target": 61}, {"id": 17, "name": ["balancing on", "attached to", "serving"], "weight": [0.33386383139913633, 0.33384511374903336, 0.33229105485183025], "source": 18, "target": 17}, {"id": 15, "name": ["grabbing", "on the other side of", "playing with"], "weight": [0.3341235777883524, 0.3335332443851589, 0.3323431778264887], "source": 18, "target": 15}, {"id": 10, "name": ["coming from", "parked beside", "leaving"], "weight": [0.33442614857174335, 0.3340943394585125, 0.3314795119697442], "source": 18, "target": 10}, {"id": 62, "name": ["has vposition"], "weight": [1.0], "source": 18, "target": 62}, {"id": 63, "name": ["has hposition"], "weight": [1.0], "source": 18, "target": 63}, {"id": 3, "name": ["flying above", "printed on", "taller than"], "weight": [0.3336868077991461, 0.33340746044361064, 0.33290573175724336], "source": 19, "target": 3}, {"id": 2, "name": ["piled on", "traveling down", "smelling"], "weight": [0.3342052234261658, 0.334052822070778, 0.3317419545030561], "source": 19, "target": 2}, {"id": 0, "name": ["looking through", "cooking", "of"], "weight": [0.33400123205187365, 0.33344607927233844, 0.3325526886757879], "source": 19, "target": 0}, {"id": 4, "name": ["close to", "looking over", "driving down"], "weight": [0.3353374256868856, 0.33468986413676216, 0.3299727101763523], "source": 19, "target": 4}, {"id": 5, "name": ["flying above", "coming down", "beneath"], "weight": [0.3346511382891292, 0.333449326221052, 0.33189953548981876], "source": 19, "target": 5}, {"id": 7, "name": ["photographing", "stacked on", "standing on"], "weight": [0.3351820728001407, 0.33285729845569706, 0.33196062874416227], "source": 19, "target": 7}, {"id": 8, "name": ["adjusting", "following", "sitting at"], "weight": [0.33393027958407673, 0.33316837396885696, 0.33290134644706626], "source": 19, "target": 8}, {"id": 13, "name": ["standing beside", "sitting at", "followed by"], "weight": [0.334161752041452, 0.33296402208291537, 0.3328742258756326], "source": 19, "target": 13}, {"id": 14, "name": ["pulling", "on the bottom of", "pushing"], "weight": [0.33370463824981367, 0.3331544068824616, 0.3331409548677247], "source": 19, "target": 14}, {"id": 15, "name": ["standing on top of", "walking down", "enclosing"], "weight": [0.3342770480273235, 0.33412211393799246, 0.331600838034684], "source": 19, "target": 15}, {"id": 64, "name": ["has vposition"], "weight": [1.0], "source": 19, "target": 64}, {"id": 65, "name": ["has hposition"], "weight": [1.0], "source": 19, "target": 65}, {"id": 66, "name": ["has vposition"], "weight": [1.0], "source": 20, "target": 66}, {"id": 67, "name": ["has hposition"], "weight": [1.0], "source": 20, "target": 67}, {"id": 68, "name": ["has vposition"], "weight": [1.0], "source": 21, "target": 68}, {"id": 69, "name": ["has hposition"], "weight": [1.0], "source": 21, "target": 69}, {"id": 70, "name": ["has vposition"], "weight": [1.0], "source": 22, "target": 70}, {"id": 71, "name": ["has hposition"], "weight": [1.0], "source": 22, "target": 71}, {"name": ["reverse has color"], "id": 0, "weight": [1.0], "source": 23, "target": 0}, {"name": ["reverse has property"], "id": 0, "weight": [1.0], "source": 24, "target": 0}, {"name": ["reverse has fatness"], "id": 0, "weight": [1.0], "source": 25, "target": 0}, {"name": ["reverse has vposition"], "id": 0, "weight": [1.0], "source": 26, "target": 0}, {"name": ["reverse has hposition"], "id": 0, "weight": [1.0], "source": 27, "target": 0}, {"name": ["reverse has vposition"], "id": 1, "weight": [1.0], "source": 28, "target": 1}, {"name": ["reverse has hposition"], "id": 1, "weight": [1.0], "source": 29, "target": 1}, {"name": ["reverse has vposition"], "id": 2, "weight": [1.0], "source": 30, "target": 2}, {"name": ["reverse has hposition"], "id": 2, "weight": [1.0], "source": 31, "target": 2}, {"name": ["reverse has vposition"], "id": 3, "weight": [1.0], "source": 32, "target": 3}, {"name": ["reverse has hposition"], "id": 3, "weight": [1.0], "source": 33, "target": 3}, {"name": ["reverse has vposition"], "id": 4, "weight": [1.0], "source": 34, "target": 4}, {"name": ["reverse has hposition"], "id": 4, "weight": [1.0], "source": 35, "target": 4}, {"name": ["reverse has vposition"], "id": 5, "weight": [1.0], "source": 36, "target": 5}, {"name": ["reverse has hposition"], "id": 5, "weight": [1.0], "source": 37, "target": 5}, {"name": ["reverse has vposition"], "id": 6, "weight": [1.0], "source": 38, "target": 6}, {"name": ["reverse has hposition"], "id": 6, "weight": [1.0], "source": 39, "target": 6}, {"name": ["reverse has vposition"], "id": 7, "weight": [1.0], "source": 40, "target": 7}, {"name": ["reverse has hposition"], "id": 7, "weight": [1.0], "source": 41, "target": 7}, {"name": ["reverse has vposition"], "id": 8, "weight": [1.0], "source": 42, "target": 8}, {"name": ["reverse has hposition"], "id": 8, "weight": [1.0], "source": 43, "target": 8}, {"name": ["reverse has vposition"], "id": 9, "weight": [1.0], "source": 44, "target": 9}, {"name": ["reverse has hposition"], "id": 9, "weight": [1.0], "source": 45, "target": 9}, {"name": ["reverse has vposition"], "id": 10, "weight": [1.0], "source": 46, "target": 10}, {"name": ["reverse has hposition"], "id": 10, "weight": [1.0], "source": 47, "target": 10}, {"name": ["reverse has vposition"], "id": 11, "weight": [1.0], "source": 48, "target": 11}, {"name": ["reverse has hposition"], "id": 11, "weight": [1.0], "source": 49, "target": 11}, {"name": ["reverse has vposition"], "id": 12, "weight": [1.0], "source": 50, "target": 12}, {"name": ["reverse has hposition"], "id": 12, "weight": [1.0], "source": 51, "target": 12}, {"name": ["reverse has vposition"], "id": 13, "weight": [1.0], "source": 52, "target": 13}, {"name": ["reverse has hposition"], "id": 13, "weight": [1.0], "source": 53, "target": 13}, {"name": ["reverse has vposition"], "id": 14, "weight": [1.0], "source": 54, "target": 14}, {"name": ["reverse has hposition"], "id": 14, "weight": [1.0], "source": 55, "target": 14}, {"name": ["reverse has vposition"], "id": 15, "weight": [1.0], "source": 56, "target": 15}, {"name": ["reverse has hposition"], "id": 15, "weight": [1.0], "source": 57, "target": 15}, {"name": ["reverse has vposition"], "id": 16, "weight": [1.0], "source": 58, "target": 16}, {"name": ["reverse has hposition"], "id": 16, "weight": [1.0], "source": 59, "target": 16}, {"name": ["reverse has vposition"], "id": 17, "weight": [1.0], "source": 60, "target": 17}, {"name": ["reverse has hposition"], "id": 17, "weight": [1.0], "source": 61, "target": 17}, {"name": ["reverse has vposition"], "id": 18, "weight": [1.0], "source": 62, "target": 18}, {"name": ["reverse has hposition"], "id": 18, "weight": [1.0], "source": 63, "target": 18}, {"name": ["reverse has vposition"], "id": 19, "weight": [1.0], "source": 64, "target": 19}, {"name": ["reverse has hposition"], "id": 19, "weight": [1.0], "source": 65, "target": 19}, {"name": ["reverse has vposition"], "id": 20, "weight": [1.0], "source": 66, "target": 20}, {"name": ["reverse has hposition"], "id": 20, "weight": [1.0], "source": 67, "target": 20}, {"name": ["reverse has vposition"], "id": 21, "weight": [1.0], "source": 68, "target": 21}, {"name": ["reverse has hposition"], "id": 21, "weight": [1.0], "source": 69, "target": 21}, {"name": ["reverse has vposition"], "id": 22, "weight": [1.0], "source": 70, "target": 22}, {"name": ["reverse has hposition"], "id": 22, "weight": [1.0], "source": 71, "target": 22}]}