{"directed": true, "multigraph": false, "graph": {}, "nodes": [{"object": "x0", "name": ["__background__", "pans", "pikachu"], "weight": [1.0, 1.0, 1.0], "id": 0}, {"object": "x1", "name": ["__background__", "pans", "pikachu"], "weight": [1.0, 1.0, 1.0], "id": 1}, {"object": "x2", "name": ["__background__", "pans", "pikachu"], "weight": [1.0, 1.0, 1.0], "id": 2}, {"object": "x3", "name": ["__background__", "pans", "pikachu"], "weight": [1.0, 1.0, 1.0], "id": 3}, {"object": "x4", "name": ["__background__", "pans", "pikachu"], "weight": [1.0, 1.0, 1.0], "id": 4}, {"object": "x5", "name": ["__background__", "pans", "pikachu"], "weight": [1.0, 1.0, 1.0], "id": 5}, {"object": "x6", "name": ["__background__", "pans", "pikachu"], "weight": [1.0, 1.0, 1.0], "id": 6}, {"object": "x7", "name": ["__background__", "pans", "pikachu"], "weight": [1.0, 1.0, 1.0], "id": 7}, {"object": "x8", "name": ["__background__", "pans", "pikachu"], "weight": [1.0, 1.0, 1.0], "id": 8}, {"object": "x9", "name": ["__background__", "pans", "pikachu"], "weight": [1.0, 1.0, 1.0], "id": 9}, {"object": "x10", "name": ["__background__", "pans", "pikachu"], "weight": [1.0, 1.0, 1.0], "id": 10}, {"object": "x11", "name": ["__background__", "pans", "pikachu"], "weight": [1.0, 1.0, 1.0], "id": 11}, {"object": "x12", "name": ["__background__", "pans", "pikachu"], "weight": [1.0, 1.0, 1.0], "id": 12}, {"object": "x13", "name": ["__background__", "pans", "pikachu"], "weight": [1.0, 1.0, 1.0], "id": 13}, {"name": ["burnt", "overhead", "shaggy"], "weight": [0.9962881750652081, 0.9925040152170312, 0.9922106862234497], "id": 14}, {"name": ["tall"], "weight": [0.9973585803709933], "id": 15}, {"name": ["round"], "weight": [0.9969467321738522], "id": 16}, {"name": ["top"], "weight": [1.0], "id": 17}, {"name": ["right"], "weight": [1.0], "id": 18}, {"name": ["top"], "weight": [1.0], "id": 19}, {"name": ["left"], "weight": [1.0], "id": 20}, {"name": ["top"], "weight": [1.0], "id": 21}, {"name": ["right"], "weight": [1.0], "id": 22}, {"name": ["top"], "weight": [1.0], "id": 23}, {"name": ["right"], "weight": [1.0], "id": 24}, {"name": ["top"], "weight": [1.0], "id": 25}, {"name": ["right"], "weight": [1.0], "id": 26}, {"name": ["bottom"], "weight": [1.0], "id": 27}, {"name": ["left"], "weight": [1.0], "id": 28}, {"name": ["top"], "weight": [1.0], "id": 29}, {"name": ["left"], "weight": [1.0], "id": 30}, {"name": ["top"], "weight": [1.0], "id": 31}, {"name": ["left"], "weight": [1.0], "id": 32}, {"name": ["top"], "weight": [1.0], "id": 33}, {"name": ["left"], "weight": [1.0], "id": 34}, {"name": ["bottom"], "weight": [1.0], "id": 35}, {"name": ["left"], "weight": [1.0], "id": 36}, {"name": ["bottom"], "weight": [1.0], "id": 37}, {"name": ["left"], "weight": [1.0], "id": 38}, {"name": ["bottom"], "weight": [1.0], "id": 39}, {"name": ["left"], "weight": [1.0], "id": 40}, {"name": ["top"], "weight": [1.0], "id": 41}, {"name": ["right"], "weight": [1.0], "id": 42}, {"name": ["top"], "weight": [1.0], "id": 43}, {"name": ["left"], "weight": [1.0], "id": 44}], "links": [{"id": 7, "name": ["tied around", "sleeping on", "grabbing"], "weight": [0.335246313376916, 0.333495650281183, 0.33125803634190093], "source": 0, "target": 7}, {"id": 1, "name": ["running across", "lying in", "hanging off"], "weight": [0.3338253700101015, 0.333379952438864, 0.3327946775510345], "source": 0, "target": 1}, {"id": 14, "name": ["has property"], "weight": [1.0], "source": 0, "target": 14}, {"id": 15, "name": ["has height"], "weight": [1.0], "source": 0, "target": 15}, {"id": 16, "name": ["has shape"], "weight": [1.0], "source": 0, "target": 16}, {"id": 17, "name": ["has vposition"], "weight": [1.0], "source": 0, "target": 17}, {"id": 18, "name": ["has hposition"], "weight": [1.0], "source": 0, "target": 18}, {"id": 9, "name": ["sitting in front of", "sitting beside", "walking down"], "weight": [0.3340823065034822, 0.3331111438560531, 0.3328065496404647], "source": 1, "target": 9}, {"id": 7, "name": ["looking into", "flying above", "riding on"], "weight": [0.3340181220711224, 0.3339819637867992, 0.3319999141420784], "source": 1, "target": 7}, {"id": 0, "name": ["staring at", "sitting inside", "looking over"], "weight": [0.33433359110570476, 0.3329212468648096, 0.3327451620294856], "source": 1, "target": 0}, {"id": 4, "name": ["opening", "lying on top of", "floating in"], "weight": [0.334413445384073, 0.3328777715799145, 0.3327087830360124], "source": 1, "target": 4}, {"id": 19, "name": ["has vposition"], "weight": [1.0], "source": 1, "target": 19}, {"id": 20, "name": ["has hposition"], "weight": [1.0], "source": 1, "target": 20}, {"id": 21, "name": ["has vposition"], "weight": [1.0], "source": 2, "target": 21}, {"id": 22, "name": ["has hposition"], "weight": [1.0], "source": 2, "target": 22}, {"id": 23, "name": ["has vposition"], "weight": [1.0], "source": 3, "target": 23}, {"id": 24, "name": ["has hposition"], "weight": [1.0], "source": 3, "target": 24}, {"id": 7, "name": ["running on", "riding", "walking through"], "weight": [0.3338541131306248, 0.3336399645046761, 0.33250592236469906], "source": 4, "target": 7}, {"id": 9, "name": ["by", "under", "covered in"], "weight": [0.334631274634918, 0.33268995444185634, 0.3326787709232257], "source": 4, "target": 9}, {"id": 1, "name": ["tying", "blowing out", "resting on"], "weight": [0.334465472929548, 0.3335767707053944, 0.33195775636505775], "source": 4, "target": 1}, {"id": 25, "name": ["has vposition"], "weight": [1.0], "source": 4, "target": 25}, {"id": 26, "name": ["has hposition"], "weight": [1.0], "source": 4, "target": 26}, {"id": 27, "name": ["has vposition"], "weight": [1.0], "source": 5, "target": 27}, {"id": 28, "name": ["has hposition"], "weight": [1.0], "source": 5, "target": 28}, {"id": 29, "name": ["has vposition"], "weight": [1.0], "source": 6, "target": 29}, {"id": 30, "name": ["has hposition"], "weight": [1.0], "source": 6, "target": 30}, {"id": 1, "name": ["underneath", "making", "full of"], "weight": [0.3336725473258677, 0.3333475750830705, 0.3329798775910617], "source": 7, "target": 1}, {"id": 0, "name": ["walking into", "stacked on", "displayed on"], "weight": [0.33398122150833925, 0.3331357381315473, 0.33288304036011346], "source": 7, "target": 0}, {"id": 4, "name": ["to the left of", "running through", "walking in"], "weight": [0.334049059874751, 0.33404550308527786, 0.33190543703997116], "source": 7, "target": 4}, {"id": 7, "name": ["grabbing", "coming down", "looking down at"], "weight": [0.334375793247188, 0.33307008493021256, 0.3325541218225994], "source": 7, "target": 7}, {"id": 31, "name": ["has vposition"], "weight": [1.0], "source": 7, "target": 31}, {"id": 32, "name": ["has hposition"], "weight": [1.0], "source": 7, "target": 32}, {"id": 33, "name": ["has vposition"], "weight": [1.0], "source": 8, "target": 33}, {"id": 34, "name": ["has hposition"], "weight": [1.0], "source": 8, "target": 34}, {"id": 4, "name": ["kicking", "approaching", "running across"], "weight": [0.3345105470308192, 0.33314362244526824, 0.3323458305239125], "source": 9, "target": 4}, {"id": 35, "name": ["has vposition"], "weight": [1.0], "source": 9, "target": 35}, {"id": 36, "name": ["has hposition"], "weight": [1.0], "source": 9, "target": 36}, {"name": ["reverse sitting in front of", "reverse sitting beside", "reverse walking down"], "id": 1, "weight": [0.3340823065034822, 0.3331111438560531, 0.3328065496404647], "source": 9, "target": 1}, {"id": 37, "name": ["has vposition"], "weight": [1.0], "source": 10, "target": 37}, {"id": 38, "name": ["has hposition"], "weight": [1.0], "source": 10, "target": 38}, {"id": 39, "name": ["has vposition"], "weight": [1.0], "source": 11, "target": 39}, {"id": 40, "name": ["has hposition"], "weight": [1.0], "source": 11, "target": 40}, {"id": 41, "name": ["has vposition"], "weight": [1.0], "source": 12, "target": 41}, {"id": 42, "name": ["has hposition"], "weight": [1.0], "source": 12, "target": 42}, {"id": 43, "name": ["has vposition"], "weight": [1.0], "source": 13, "target": 43}, {"id": 44, "name": ["has hposition"], "weight": [1.0], "source": 13, "target": 44}, {"name": ["reverse has property"], "id": 0, "weight": [1.0], "source": 14, "target": 0}, {"name": ["reverse has height"], "id": 0, "weight": [1.0], "source": 15, "target": 0}, {"name": ["reverse has shape"], "id": 0, "weight": [1.0], "source": 16, "target": 0}, {"name": ["reverse has vposition"], "id": 0, "weight": [1.0], "source": 17, "target": 0}, {"name": ["reverse has hposition"], "id": 0, "weight": [1.0], "source": 18, "target": 0}, {"name": ["reverse has vposition"], "id": 1, "weight": [1.0], "source": 19, "target": 1}, {"name": ["reverse has hposition"], "id": 1, "weight": [1.0], "source": 20, "target": 1}, {"name": ["reverse has vposition"], "id": 2, "weight": [1.0], "source": 21, "target": 2}, {"name": ["reverse has hposition"], "id": 2, "weight": [1.0], "source": 22, "target": 2}, {"name": ["reverse has vposition"], "id": 3, "weight": [1.0], "source": 23, "target": 3}, {"name": ["reverse has hposition"], "id": 3, "weight": [1.0], "source": 24, "target": 3}, {"name": ["reverse has vposition"], "id": 4, "weight": [1.0], "source": 25, "target": 4}, {"name": ["reverse has hposition"], "id": 4, "weight": [1.0], "source": 26, "target": 4}, {"name": ["reverse has vposition"], "id": 5, "weight": [1.0], "source": 27, "target": 5}, {"name": ["reverse has hposition"], "id": 5, "weight": [1.0], "source": 28, "target": 5}, {"name": ["reverse has vposition"], "id": 6, "weight": [1.0], "source": 29, "target": 6}, {"name": ["reverse has hposition"], "id": 6, "weight": [1.0], "source": 30, "target": 6}, {"name": ["reverse has vposition"], "id": 7, "weight": [1.0], "source": 31, "target": 7}, {"name": ["reverse has hposition"], "id": 7, "weight": [1.0], "source": 32, "target": 7}, {"name": ["reverse has vposition"], "id": 8, "weight": [1.0], "source": 33, "target": 8}, {"name": ["reverse has hposition"], "id": 8, "weight": [1.0], "source": 34, "target": 8}, {"name": ["reverse has vposition"], "id": 9, "weight": [1.0], "source": 35, "target": 9}, {"name": ["reverse has hposition"], "id": 9, "weight": [1.0], "source": 36, "target": 9}, {"name": ["reverse has vposition"], "id": 10, "weight": [1.0], "source": 37, "target": 10}, {"name": ["reverse has hposition"], "id": 10, "weight": [1.0], "source": 38, "target": 10}, {"name": ["reverse has vposition"], "id": 11, "weight": [1.0], "source": 39, "target": 11}, {"name": ["reverse has hposition"], "id": 11, "weight": [1.0], "source": 40, "target": 11}, {"name": ["reverse has vposition"], "id": 12, "weight": [1.0], "source": 41, "target": 12}, {"name": ["reverse has hposition"], "id": 12, "weight": [1.0], "source": 42, "target": 12}, {"name": ["reverse has vposition"], "id": 13, "weight": [1.0], "source": 43, "target": 13}, {"name": ["reverse has hposition"], "id": 13, "weight": [1.0], "source": 44, "target": 13}]}