{"directed": true, "multigraph": false, "graph": {}, "nodes": [{"object": "x0", "name": ["__background__", "pans", "pikachu"], "weight": [1.0, 1.0, 1.0], "id": 0}, {"object": "x1", "name": ["__background__", "pans", "pikachu"], "weight": [1.0, 1.0, 1.0], "id": 1}, {"object": "x2", "name": ["__background__", "pans", "pikachu"], "weight": [1.0, 1.0, 1.0], "id": 2}, {"object": "x3", "name": ["__background__", "pans", "pikachu"], "weight": [1.0, 1.0, 1.0], "id": 3}, {"object": "x4", "name": ["__background__", "pans", "pikachu"], "weight": [1.0, 1.0, 1.0], "id": 4}, {"object": "x5", "name": ["__background__", "pans", "pikachu"], "weight": [1.0, 1.0, 1.0], "id": 5}, {"object": "x6", "name": ["__background__", "pans", "pikachu"], "weight": [1.0, 1.0, 1.0], "id": 6}, {"object": "x7", "name": ["__background__", "pans", "pikachu"], "weight": [1.0, 1.0, 1.0], "id": 7}, {"object": "x8", "name": ["__background__", "pans", "pikachu"], "weight": [1.0, 1.0, 1.0], "id": 8}, {"name": ["handmade"], "weight": [0.9987390085214043], "id": 9}, {"name": ["tinted"], "weight": [0.9955443494486346], "id": 10}, {"name": ["cream colored"], "weight": [0.9949977936352913], "id": 11}, {"name": ["top"], "weight": [1.0], "id": 12}, {"name": ["right"], "weight": [1.0], "id": 13}, {"name": ["top"], "weight": [1.0], "id": 14}, {"name": ["left"], "weight": [1.0], "id": 15}, {"name": ["top"], "weight": [1.0], "id": 16}, {"name": ["right"], "weight": [1.0], "id": 17}, {"name": ["bottom"], "weight": [1.0], "id": 18}, {"name": ["right"], "weight": [1.0], "id": 19}, {"name": ["bottom"], "weight": [1.0], "id": 20}, {"name": ["right"], "weight": [1.0], "id": 21}, {"name": ["top"], "weight": [1.0], "id": 22}, {"name": ["left"], "weight": [1.0], "id": 23}, {"name": ["top"], "weight": [1.0], "id": 24}, {"name": ["left"], "weight": [1.0], "id": 25}, {"name": ["bottom"], "weight": [1.0], "id": 26}, {"name": ["right"], "weight": [1.0], "id": 27}, {"name": ["bottom"], "weight": [1.0], "id": 28}, {"name": ["left"], "weight": [1.0], "id": 29}], "links": [{"id": 3, "name": ["staring at", "connected to", "sitting at"], "weight": [0.33373091184520237, 0.33360835540911915, 0.33266073274567853], "source": 0, "target": 3}, {"id": 8, "name": ["hanging over", "washing", "growing next to"], "weight": [0.3342515902376572, 0.3339308352275806, 0.33181757453476224], "source": 0, "target": 8}, {"id": 2, "name": ["moving", "on the edge of", "covering"], "weight": [0.33453736225445685, 0.3329447841125708, 0.33251785363297237], "source": 0, "target": 2}, {"id": 9, "name": ["has property"], "weight": [1.0], "source": 0, "target": 9}, {"id": 10, "name": ["has cleanliness"], "weight": [1.0], "source": 0, "target": 10}, {"id": 11, "name": ["has color"], "weight": [1.0], "source": 0, "target": 11}, {"id": 12, "name": ["has vposition"], "weight": [1.0], "source": 0, "target": 12}, {"id": 13, "name": ["has hposition"], "weight": [1.0], "source": 0, "target": 13}, {"id": 14, "name": ["has vposition"], "weight": [1.0], "source": 1, "target": 14}, {"id": 15, "name": ["has hposition"], "weight": [1.0], "source": 1, "target": 15}, {"id": 0, "name": ["kissing", "displayed on", "by"], "weight": [0.33397745962004155, 0.333380574949698, 0.33264196543026037], "source": 2, "target": 0}, {"id": 16, "name": ["has vposition"], "weight": [1.0], "source": 2, "target": 16}, {"id": 17, "name": ["has hposition"], "weight": [1.0], "source": 2, "target": 17}, {"id": 3, "name": ["playing in", "covered in", "entering"], "weight": [0.3351239928737952, 0.33252356998882443, 0.3323524371373804], "source": 3, "target": 3}, {"id": 0, "name": ["flying", "grabbing", "sitting in"], "weight": [0.3346465299066313, 0.3336346285445489, 0.3317188415488199], "source": 3, "target": 0}, {"id": 8, "name": ["running in", "skiing on", "sitting beside"], "weight": [0.33459930827375345, 0.3328361002001991, 0.3325645915260474], "source": 3, "target": 8}, {"id": 18, "name": ["has vposition"], "weight": [1.0], "source": 3, "target": 18}, {"id": 19, "name": ["has hposition"], "weight": [1.0], "source": 3, "target": 19}, {"id": 20, "name": ["has vposition"], "weight": [1.0], "source": 4, "target": 20}, {"id": 21, "name": ["has hposition"], "weight": [1.0], "source": 4, "target": 21}, {"id": 22, "name": ["has vposition"], "weight": [1.0], "source": 5, "target": 22}, {"id": 23, "name": ["has hposition"], "weight": [1.0], "source": 5, "target": 23}, {"id": 24, "name": ["has vposition"], "weight": [1.0], "source": 6, "target": 24}, {"id": 25, "name": ["has hposition"], "weight": [1.0], "source": 6, "target": 25}, {"id": 26, "name": ["has vposition"], "weight": [1.0], "source": 7, "target": 26}, {"id": 27, "name": ["has hposition"], "weight": [1.0], "source": 7, "target": 27}, {"id": 3, "name": ["filled with", "sitting beside", "lying in"], "weight": [0.3335469668286358, 0.3332608770927933, 0.3331921560785709], "source": 8, "target": 3}, {"id": 0, "name": ["tying", "lying next to", "beneath"], "weight": [0.3337878882722402, 0.333616755019315, 0.3325953567084448], "source": 8, "target": 0}, {"id": 28, "name": ["has vposition"], "weight": [1.0], "source": 8, "target": 28}, {"id": 29, "name": ["has hposition"], "weight": [1.0], "source": 8, "target": 29}, {"name": ["reverse has property"], "id": 0, "weight": [1.0], "source": 9, "target": 0}, {"name": ["reverse has cleanliness"], "id": 0, "weight": [1.0], "source": 10, "target": 0}, {"name": ["reverse has color"], "id": 0, "weight": [1.0], "source": 11, "target": 0}, {"name": ["reverse has vposition"], "id": 0, "weight": [1.0], "source": 12, "target": 0}, {"name": ["reverse has hposition"], "id": 0, "weight": [1.0], "source": 13, "target": 0}, {"name": ["reverse has vposition"], "id": 1, "weight": [1.0], "source": 14, "target": 1}, {"name": ["reverse has hposition"], "id": 1, "weight": [1.0], "source": 15, "target": 1}, {"name": ["reverse has vposition"], "id": 2, "weight": [1.0], "source": 16, "target": 2}, {"name": ["reverse has hposition"], "id": 2, "weight": [1.0], "source": 17, "target": 2}, {"name": ["reverse has vposition"], "id": 3, "weight": [1.0], "source": 18, "target": 3}, {"name": ["reverse has hposition"], "id": 3, "weight": [1.0], "source": 19, "target": 3}, {"name": ["reverse has vposition"], "id": 4, "weight": [1.0], "source": 20, "target": 4}, {"name": ["reverse has hposition"], "id": 4, "weight": [1.0], "source": 21, "target": 4}, {"name": ["reverse has vposition"], "id": 5, "weight": [1.0], "source": 22, "target": 5}, {"name": ["reverse has hposition"], "id": 5, "weight": [1.0], "source": 23, "target": 5}, {"name": ["reverse has vposition"], "id": 6, "weight": [1.0], "source": 24, "target": 6}, {"name": ["reverse has hposition"], "id": 6, "weight": [1.0], "source": 25, "target": 6}, {"name": ["reverse has vposition"], "id": 7, "weight": [1.0], "source": 26, "target": 7}, {"name": ["reverse has hposition"], "id": 7, "weight": [1.0], "source": 27, "target": 7}, {"name": ["reverse has vposition"], "id": 8, "weight": [1.0], "source": 28, "target": 8}, {"name": ["reverse has hposition"], "id": 8, "weight": [1.0], "source": 29, "target": 8}]}