{"directed": true, "multigraph": false, "graph": {}, "nodes": [{"object": "x0", "name": ["__background__", "pans", "pikachu"], "weight": [1.0, 1.0, 1.0], "id": 0}, {"object": "x1", "name": ["__background__", "pans", "pikachu"], "weight": [1.0, 1.0, 1.0], "id": 1}, {"object": "x2", "name": ["__background__", "pans", "pikachu"], "weight": [1.0, 1.0, 1.0], "id": 2}, {"object": "x3", "name": ["__background__", "pans", "pikachu"], "weight": [1.0, 1.0, 1.0], "id": 3}, {"object": "x4", "name": ["__background__", "pans", "pikachu"], "weight": [1.0, 1.0, 1.0], "id": 4}, {"object": "x5", "name": ["__background__", "pans", "pikachu"], "weight": [1.0, 1.0, 1.0], "id": 5}, {"object": "x6", "name": ["__background__", "pans", "pikachu"], "weight": [1.0, 1.0, 1.0], "id": 6}, {"object": "x7", "name": ["__background__", "pans", "pikachu"], "weight": [1.0, 1.0, 1.0], "id": 7}, {"object": "x8", "name": ["__background__", "pans", "pikachu"], "weight": [1.0, 1.0, 1.0], "id": 8}, {"object": "x9", "name": ["__background__", "pans", "pikachu"], "weight": [1.0, 1.0, 1.0], "id": 9}, {"object": "x10", "name": ["__background__", "pans", "pikachu"], "weight": [1.0, 1.0, 1.0], "id": 10}, {"name": ["aluminum"], "weight": [0.997452592104391], "id": 11}, {"name": ["wide"], "weight": [0.9964788433517539], "id": 12}, {"name": ["puffy"], "weight": [0.996373036430244], "id": 13}, {"name": ["top"], "weight": [1.0], "id": 14}, {"name": ["right"], "weight": [1.0], "id": 15}, {"name": ["bottom"], "weight": [1.0], "id": 16}, {"name": ["right"], "weight": [1.0], "id": 17}, {"name": ["top"], "weight": [1.0], "id": 18}, {"name": ["right"], "weight": [1.0], "id": 19}, {"name": ["top"], "weight": [1.0], "id": 20}, {"name": ["right"], "weight": [1.0], "id": 21}, {"name": ["top"], "weight": [1.0], "id": 22}, {"name": ["right"], "weight": [1.0], "id": 23}, {"name": ["top"], "weight": [1.0], "id": 24}, {"name": ["right"], "weight": [1.0], "id": 25}, {"name": ["top"], "weight": [1.0], "id": 26}, {"name": ["left"], "weight": [1.0], "id": 27}, {"name": ["top"], "weight": [1.0], "id": 28}, {"name": ["right"], "weight": [1.0], "id": 29}, {"name": ["top"], "weight": [1.0], "id": 30}, {"name": ["left"], "weight": [1.0], "id": 31}, {"name": ["top"], "weight": [1.0], "id": 32}, {"name": ["right"], "weight": [1.0], "id": 33}, {"name": ["top"], "weight": [1.0], "id": 34}, {"name": ["left"], "weight": [1.0], "id": 35}], "links": [{"id": 0, "name": ["petting", "displayed on", "hanging in"], "weight": [0.3347418683340551, 0.33289942132532735, 0.33235871034061754], "source": 0, "target": 0}, {"id": 2, "name": ["traveling down", "opening", "reflected on"], "weight": [0.33390897193529534, 0.33370679137688103, 0.3323842366878237], "source": 0, "target": 2}, {"id": 9, "name": ["on the other side of", "above", "holding onto"], "weight": [0.3342022491169533, 0.3337567378567305, 0.33204101302631617], "source": 0, "target": 9}, {"id": 8, "name": ["standing in front of", "coming down", "displayed on"], "weight": [0.3336773288980771, 0.3335987190018663, 0.3327239521000567], "source": 0, "target": 8}, {"id": 5, "name": ["standing near", "connected to", "looking out"], "weight": [0.33383289940900096, 0.33380823971831375, 0.33235886087268535], "source": 0, "target": 5}, {"id": 3, "name": ["to the right of", "observing", "looking into"], "weight": [0.33421894170199196, 0.334022047411994, 0.33175901088601406], "source": 0, "target": 3}, {"id": 11, "name": ["has material"], "weight": [1.0], "source": 0, "target": 11}, {"id": 12, "name": ["has width"], "weight": [1.0], "source": 0, "target": 12}, {"id": 13, "name": ["has property"], "weight": [1.0], "source": 0, "target": 13}, {"id": 14, "name": ["has vposition"], "weight": [1.0], "source": 0, "target": 14}, {"id": 15, "name": ["has hposition"], "weight": [1.0], "source": 0, "target": 15}, {"name": ["reverse observing", "reverse sitting beside", "reverse photographing"], "id": 1, "weight": [0.3340396939192406, 0.3330931734996901, 0.33286713258106926], "source": 0, "target": 1}, {"id": 0, "name": ["observing", "sitting beside", "photographing"], "weight": [0.3340396939192406, 0.3330931734996901, 0.33286713258106926], "source": 1, "target": 0}, {"id": 9, "name": ["mounted on", "smelling", "coming from"], "weight": [0.33409310653029894, 0.33296796377130833, 0.3329389296983927], "source": 1, "target": 9}, {"id": 16, "name": ["has vposition"], "weight": [1.0], "source": 1, "target": 16}, {"id": 17, "name": ["has hposition"], "weight": [1.0], "source": 1, "target": 17}, {"id": 0, "name": ["working on", "near", "sitting in"], "weight": [0.33408477290027583, 0.3332165218633125, 0.33269870523641176], "source": 2, "target": 0}, {"id": 3, "name": ["on the back of", "covered with", "hanging over"], "weight": [0.33413438427756953, 0.3339259794562279, 0.33193963626620254], "source": 2, "target": 3}, {"id": 9, "name": ["parked behind", "sitting around", "piled on"], "weight": [0.33426490670411124, 0.3338693340004385, 0.33186575929545026], "source": 2, "target": 9}, {"id": 18, "name": ["has vposition"], "weight": [1.0], "source": 2, "target": 18}, {"id": 19, "name": ["has hposition"], "weight": [1.0], "source": 2, "target": 19}, {"id": 0, "name": ["stuck in", "kept in", "bigger than"], "weight": [0.33360871976231093, 0.33338023640264414, 0.33301104383504493], "source": 3, "target": 0}, {"id": 3, "name": ["followed by", "coming from", "pushing"], "weight": [0.33424691485610586, 0.33299832559613207, 0.332754759547762], "source": 3, "target": 3}, {"id": 8, "name": ["standing against", "flying", "sitting on"], "weight": [0.3343298373881987, 0.33417604232093057, 0.3314941202908708], "source": 3, "target": 8}, {"id": 5, "name": ["walking by", "traveling down", "walking through"], "weight": [0.3342624569650641, 0.3335863244045199, 0.3321512186304159], "source": 3, "target": 5}, {"id": 2, "name": ["following", "wading in", "drawn on"], "weight": [0.3336327614194105, 0.33320599279059854, 0.3331612457899909], "source": 3, "target": 2}, {"id": 20, "name": ["has vposition"], "weight": [1.0], "source": 3, "target": 20}, {"id": 21, "name": ["has hposition"], "weight": [1.0], "source": 3, "target": 21}, {"id": 22, "name": ["has vposition"], "weight": [1.0], "source": 4, "target": 22}, {"id": 23, "name": ["has hposition"], "weight": [1.0], "source": 4, "target": 23}, {"id": 9, "name": ["in", "sitting at", "touching"], "weight": [0.3343030967486311, 0.33330074801045206, 0.33239615524091687], "source": 5, "target": 9}, {"id": 5, "name": ["picking up", "leaving", "grabbing"], "weight": [0.334015943490992, 0.3332819934684634, 0.3327020630405446], "source": 5, "target": 5}, {"id": 0, "name": ["following", "growing from", "of"], "weight": [0.33480245788757457, 0.33316504697287325, 0.3320324951395522], "source": 5, "target": 0}, {"id": 8, "name": ["helping", "talking to", "boarding"], "weight": [0.3343564613433217, 0.33388877502877956, 0.3317547636278988], "source": 5, "target": 8}, {"id": 3, "name": ["resting on", "walking up", "working on"], "weight": [0.3333762683027048, 0.3333268031993679, 0.3332969284979272], "source": 5, "target": 3}, {"id": 24, "name": ["has vposition"], "weight": [1.0], "source": 5, "target": 24}, {"id": 25, "name": ["has hposition"], "weight": [1.0], "source": 5, "target": 25}, {"id": 26, "name": ["has vposition"], "weight": [1.0], "source": 6, "target": 26}, {"id": 27, "name": ["has hposition"], "weight": [1.0], "source": 6, "target": 27}, {"id": 28, "name": ["has vposition"], "weight": [1.0], "source": 7, "target": 28}, {"id": 29, "name": ["has hposition"], "weight": [1.0], "source": 7, "target": 29}, {"id": 5, "name": ["skiing in", "on top of", "sitting by"], "weight": [0.33406022971499383, 0.3332332932360363, 0.33270647704896994], "source": 8, "target": 5}, {"id": 0, "name": ["mounted to", "sitting at", "full of"], "weight": [0.3364225440269465, 0.33240656218197673, 0.3311708937910769], "source": 8, "target": 0}, {"id": 3, "name": ["coming out of", "filled with", "smaller than"], "weight": [0.3341304143078748, 0.33388675800933443, 0.3319828276827908], "source": 8, "target": 3}, {"id": 30, "name": ["has vposition"], "weight": [1.0], "source": 8, "target": 30}, {"id": 31, "name": ["has hposition"], "weight": [1.0], "source": 8, "target": 31}, {"id": 5, "name": ["holding", "sitting at", "walking along"], "weight": [0.334964662388842, 0.33416758764753063, 0.33086774996362733], "source": 9, "target": 5}, {"id": 0, "name": ["coming from", "hugging", "driving down"], "weight": [0.33398612917457854, 0.3335656561093029, 0.3324482147161185], "source": 9, "target": 0}, {"id": 2, "name": ["covered by", "grazing in", "smelling"], "weight": [0.3338899561255587, 0.3331888073830215, 0.33292123649141975], "source": 9, "target": 2}, {"id": 32, "name": ["has vposition"], "weight": [1.0], "source": 9, "target": 32}, {"id": 33, "name": ["has hposition"], "weight": [1.0], "source": 9, "target": 33}, {"name": ["reverse mounted on", "reverse smelling", "reverse coming from"], "id": 1, "weight": [0.33409310653029894, 0.33296796377130833, 0.3329389296983927], "source": 9, "target": 1}, {"id": 34, "name": ["has vposition"], "weight": [1.0], "source": 10, "target": 34}, {"id": 35, "name": ["has hposition"], "weight": [1.0], "source": 10, "target": 35}, {"name": ["reverse has material"], "id": 0, "weight": [1.0], "source": 11, "target": 0}, {"name": ["reverse has width"], "id": 0, "weight": [1.0], "source": 12, "target": 0}, {"name": ["reverse has property"], "id": 0, "weight": [1.0], "source": 13, "target": 0}, {"name": ["reverse has vposition"], "id": 0, "weight": [1.0], "source": 14, "target": 0}, {"name": ["reverse has hposition"], "id": 0, "weight": [1.0], "source": 15, "target": 0}, {"name": ["reverse has vposition"], "id": 1, "weight": [1.0], "source": 16, "target": 1}, {"name": ["reverse has hposition"], "id": 1, "weight": [1.0], "source": 17, "target": 1}, {"name": ["reverse has vposition"], "id": 2, "weight": [1.0], "source": 18, "target": 2}, {"name": ["reverse has hposition"], "id": 2, "weight": [1.0], "source": 19, "target": 2}, {"name": ["reverse has vposition"], "id": 3, "weight": [1.0], "source": 20, "target": 3}, {"name": ["reverse has hposition"], "id": 3, "weight": [1.0], "source": 21, "target": 3}, {"name": ["reverse has vposition"], "id": 4, "weight": [1.0], "source": 22, "target": 4}, {"name": ["reverse has hposition"], "id": 4, "weight": [1.0], "source": 23, "target": 4}, {"name": ["reverse has vposition"], "id": 5, "weight": [1.0], "source": 24, "target": 5}, {"name": ["reverse has hposition"], "id": 5, "weight": [1.0], "source": 25, "target": 5}, {"name": ["reverse has vposition"], "id": 6, "weight": [1.0], "source": 26, "target": 6}, {"name": ["reverse has hposition"], "id": 6, "weight": [1.0], "source": 27, "target": 6}, {"name": ["reverse has vposition"], "id": 7, "weight": [1.0], "source": 28, "target": 7}, {"name": ["reverse has hposition"], "id": 7, "weight": [1.0], "source": 29, "target": 7}, {"name": ["reverse has vposition"], "id": 8, "weight": [1.0], "source": 30, "target": 8}, {"name": ["reverse has hposition"], "id": 8, "weight": [1.0], "source": 31, "target": 8}, {"name": ["reverse has vposition"], "id": 9, "weight": [1.0], "source": 32, "target": 9}, {"name": ["reverse has hposition"], "id": 9, "weight": [1.0], "source": 33, "target": 9}, {"name": ["reverse has vposition"], "id": 10, "weight": [1.0], "source": 34, "target": 10}, {"name": ["reverse has hposition"], "id": 10, "weight": [1.0], "source": 35, "target": 10}]}